[
  {
    "gender": "Girl",
    "id": 947665,
    "meaning": "A bright and shining ray of light",
    "name": "elladine",
    "origin": "Arabic",
    "religion": "",
    "soundUrl": "https://cdn2.momjunction.com/wp-content/uploads/baby-names/audio_files/elladine-arabic.mp3"
  },
  {
    "gender": "Girl",
    "id": 947667,
    "meaning": "A gift sent from heaven; one who is filled with light",
    "name": "elladora",
    "origin": "Greek",
    "religion": "Christianity",
    "soundUrl": "https://cdn2.momjunction.com/wp-content/uploads/baby-names/audio_files/elladora-english.mp3"
  },
  {
    "gender": "Girl",
    "id": 947673,
    "meaning": "A combination name; One who is true to all",
    "name": "ellamae",
    "origin": "English,Gothic",
    "religion": "Christianity",
    "soundUrl": "https://cdn2.momjunction.com/wp-content/uploads/baby-names/audio_files/ellamae-english.mp3"
  },
  {
    "gender": "Girl",
    "id": 947682,
    "meaning": "Bright and shining light of magic",
    "name": "ellan",
    "origin": "Anglo Saxon",
    "religion": "Christianity",
    "soundUrl": "https://cdn2.momjunction.com/wp-content/uploads/baby-names/audio_files/ellan-english.mp3"
  },
  {
    "gender": "Girl",
    "id": 947709,
    "meaning": "Children of Ellis; Creative; Productive",
    "name": "ellasyn",
    "origin": "United States",
    "religion": "Christianity",
    "soundUrl": "https://cdn2.momjunction.com/wp-content/uploads/baby-names/audio_files/ellasyn-english.mp3"
  },
  {
    "gender": "Girl",
    "id": 947735,
    "meaning": "Sun ray; Light",
    "name": "elle",
    "origin": "United States",
    "religion": "Christianity",
    "soundUrl": "https://cdn2.momjunction.com/wp-content/uploads/baby-names/audio_files/elle-english.mp3"
  },
  {
    "gender": "Girl",
    "id": 947747,
    "meaning": "One who is foreign and is true to all",
    "name": "ellea",
    "origin": "German",
    "religion": "Christianity",
    "soundUrl": "https://cdn2.momjunction.com/wp-content/uploads/baby-names/audio_files/ellea-german.mp3"
  },
  {
    "gender": "Girl",
    "id": 947754,
    "meaning": "Shining God who shows light to all; Bright torch",
    "name": "elleanor",
    "origin": "Greek",
    "religion": "Christianity",
    "soundUrl": "https://cdn2.momjunction.com/wp-content/uploads/baby-names/audio_files/elleanor-english.mp3"
  },
  {
    "gender": "Girl",
    "id": 947767,
    "meaning": "Form of Elijah; An ideal human being",
    "name": "ellecia",
    "origin": "Greek",
    "religion": "Christianity",
    "soundUrl": "https://cdn2.momjunction.com/wp-content/uploads/baby-names/audio_files/ellecia-english.mp3"
  },
  {
    "gender": "Girl",
    "id": 947770,
    "meaning": "One who works with everyone; A creative and excellent person",
    "name": "ellee",
    "origin": "English",
    "religion": "Christianity",
    "soundUrl": "https://cdn2.momjunction.com/wp-content/uploads/baby-names/audio_files/ellee-english.mp3"
  },
  {
    "gender": "Girl",
    "id": 947779,
    "meaning": "An efficient person who milks the Cow",
    "name": "ellema",
    "origin": "African",
    "religion": "Christianity",
    "soundUrl": "https://cdn2.momjunction.com/wp-content/uploads/baby-names/audio_files/ellema-english.mp3"
  },
  {
    "gender": "Girl",
    "id": 947781,
    "meaning": "Bright; Shining light",
    "name": "ellen",
    "origin": "English",
    "religion": "Christianity",
    "soundUrl": "https://cdn2.momjunction.com/wp-content/uploads/baby-names/audio_files/ellen-english.mp3"
  },
  {
    "gender": "Girl",
    "id": 947792,
    "meaning": "Light; Torch",
    "name": "ellena",
    "origin": "English",
    "religion": "Christianity",
    "soundUrl": "https://cdn2.momjunction.com/wp-content/uploads/baby-names/audio_files/ellena-english.mp3"
  },
  {
    "gender": "Girl",
    "id": 947800,
    "meaning": "A bright and shining light; Deep inner sense; eautiful",
    "name": "ellene",
    "origin": "Greek",
    "religion": "Christianity",
    "soundUrl": "https://cdn2.momjunction.com/wp-content/uploads/baby-names/audio_files/ellene-english.mp3"
  },
  {
    "gender": "Girl",
    "id": 947805,
    "meaning": "Light",
    "name": "ellenmae",
    "origin": "English",
    "religion": "Christianity",
    "soundUrl": "https://cdn2.momjunction.com/wp-content/uploads/baby-names/audio_files/ellenmae-english.mp3"
  },
  {
    "gender": "Girl",
    "id": 947809,
    "meaning": "A bright and shining light; The God of light",
    "name": "ellenor",
    "origin": "Greek",
    "religion": "Christianity",
    "soundUrl": "https://cdn2.momjunction.com/wp-content/uploads/baby-names/audio_files/ellenor-english.mp3"
  },
  {
    "gender": "Girl",
    "id": 947821,
    "meaning": "One who is from a foreign land; Sun\u0027s ray; God is light",
    "name": "ellenora",
    "origin": "Greek",
    "religion": "Christianity",
    "soundUrl": "https://cdn2.momjunction.com/wp-content/uploads/baby-names/audio_files/ellenora-english.mp3"
  },
  {
    "gender": "Girl",
    "id": 947833,
    "meaning": "A foreign individual; Versatile and creative",
    "name": "ellenore",
    "origin": "Old French",
    "religion": "Christianity",
    "soundUrl": "https://cdn2.momjunction.com/wp-content/uploads/baby-names/audio_files/ellenore-english.mp3"
  },
  {
    "gender": "Girl",
    "id": 947838,
    "meaning": "Bright; A form of Helen",
    "name": "elleny",
    "origin": "English",
    "religion": "Christianity",
    "soundUrl": "https://cdn2.momjunction.com/wp-content/uploads/baby-names/audio_files/elleny-english.mp3"
  },
  {
    "gender": "Girl",
    "id": 947861,
    "meaning": "One who came from Alyssum flower",
    "name": "ellesa",
    "origin": "English",
    "religion": "Christianity",
    "soundUrl": "https://cdn2.momjunction.com/wp-content/uploads/baby-names/audio_files/ellesa-english.mp3"
  },
  {
    "gender": "Girl",
    "id": 947863,
    "meaning": "The bountiful God; Salvation",
    "name": "ellesha",
    "origin": "Hebrew",
    "religion": "Christianity",
    "soundUrl": "https://cdn2.momjunction.com/wp-content/uploads/baby-names/audio_files/ellesha-english.mp3"
  },
  {
    "gender": "Girl",
    "id": 947877,
    "meaning": "One with a noble, charming and friendly nature",
    "name": "ellessa",
    "origin": "English",
    "religion": "Christianity",
    "soundUrl": "https://cdn2.momjunction.com/wp-content/uploads/baby-names/audio_files/ellessa-english.mp3"
  },
  {
    "gender": "Girl",
    "id": 947880,
    "meaning": "One who is stable and loves family",
    "name": "ellesse",
    "origin": "English",
    "religion": "Christianity",
    "soundUrl": "https://cdn2.momjunction.com/wp-content/uploads/baby-names/audio_files/ellesse-english.mp3"
  },
  {
    "gender": "Girl",
    "id": 947890,
    "meaning": "A magical Elf with powers",
    "name": "elletta",
    "origin": "English",
    "religion": "Christianity",
    "soundUrl": "https://cdn2.momjunction.com/wp-content/uploads/baby-names/audio_files/elletta-english.mp3"
  },
  {
    "gender": "Girl",
    "id": 947893,
    "meaning": "A little, magical Elf",
    "name": "ellette",
    "origin": "Anglo Saxon",
    "religion": "Christianity",
    "soundUrl": "https://cdn2.momjunction.com/wp-content/uploads/baby-names/audio_files/ellette-english.mp3"
  },
  {
    "gender": "Girl",
    "id": 947895,
    "meaning": "One who is born to create harmony",
    "name": "ellexis",
    "origin": "English",
    "religion": "Christianity",
    "soundUrl": "https://cdn2.momjunction.com/wp-content/uploads/baby-names/audio_files/ellexis-english.mp3"
  },
  {
    "gender": "Girl",
    "id": 947904,
    "meaning": "One who is very powerful; an Elf",
    "name": "ellfreda",
    "origin": "Old English",
    "religion": "Christianity",
    "soundUrl": "https://cdn2.momjunction.com/wp-content/uploads/baby-names/audio_files/ellfreda-english.mp3"
  },
  {
    "gender": "Girl",
    "id": 947909,
    "meaning": "One who has the strength of a powerful Elf",
    "name": "ellfredda",
    "origin": "English",
    "religion": "Christianity",
    "soundUrl": "https://cdn2.momjunction.com/wp-content/uploads/baby-names/audio_files/ellfredda-english.mp3"
  },
  {
    "gender": "Girl",
    "id": 947914,
    "meaning": "A born Elf; A magical counsel",
    "name": "ellfreeda",
    "origin": "German",
    "religion": "Christianity",
    "soundUrl": "https://cdn2.momjunction.com/wp-content/uploads/baby-names/audio_files/ellfreeda-german.mp3"
  },
  {
    "gender": "Girl",
    "id": 947919,
    "meaning": "A powerful and magical creature; an Elf",
    "name": "ellfrida",
    "origin": "German",
    "religion": "Christianity",
    "soundUrl": "https://cdn2.momjunction.com/wp-content/uploads/baby-names/audio_files/ellfrida-german.mp3"
  },
  {
    "gender": "Girl",
    "id": 947920,
    "meaning": "A magical and powerful counsel",
    "name": "ellfrieda",
    "origin": "German",
    "religion": "Christianity",
    "soundUrl": "https://cdn2.momjunction.com/wp-content/uploads/baby-names/audio_files/ellfrieda-german.mp3"
  },
  {
    "gender": "Girl",
    "id": 947923,
    "meaning": "One who has magical strength",
    "name": "ellfryda",
    "origin": "English",
    "religion": "Christianity",
    "soundUrl": "https://cdn2.momjunction.com/wp-content/uploads/baby-names/audio_files/ellfryda-english.mp3"
  },
  {
    "gender": "Girl",
    "id": 947927,
    "meaning": "One who has massive power and strength",
    "name": "ellfrydah",
    "origin": "German",
    "religion": "Christianity",
    "soundUrl": "https://cdn2.momjunction.com/wp-content/uploads/baby-names/audio_files/ellfrydah-german.mp3"
  },
  {
    "gender": "Girl",
    "id": 947937,
    "meaning": "A kind and devoted individual",
    "name": "elli",
    "origin": "German,Hebrew",
    "religion": "Christianity",
    "soundUrl": "https://cdn2.momjunction.com/wp-content/uploads/baby-names/audio_files/elli-german.mp3"
  },
  {
    "gender": "Girl",
    "id": 947942,
    "meaning": "One who gives out Light",
    "name": "ellia",
    "origin": "English",
    "religion": "Christianity",
    "soundUrl": "https://cdn2.momjunction.com/wp-content/uploads/baby-names/audio_files/ellia-english.mp3"
  },
  {
    "gender": "Girl",
    "id": 947952,
    "meaning": "My God has answered",
    "name": "elliana",
    "origin": "Hebrew",
    "religion": "Christianity",
    "soundUrl": "https://cdn2.momjunction.com/wp-content/uploads/baby-names/audio_files/elliana-english.mp3"
  },
  {
    "gender": "Girl",
    "id": 947967,
    "meaning": "Answer to God\u0027s prayers",
    "name": "ellianna",
    "origin": "Hebrew",
    "religion": "Christianity",
    "soundUrl": "https://cdn2.momjunction.com/wp-content/uploads/baby-names/audio_files/ellianna-english.mp3"
  },
  {
    "gender": "Girl",
    "id": 947996,
    "meaning": "One who is born out of Sun",
    "name": "elliauna",
    "origin": "Latin",
    "religion": "Christianity",
    "soundUrl": "https://cdn2.momjunction.com/wp-content/uploads/baby-names/audio_files/elliauna-english.mp3"
  },
  {
    "gender": "Girl",
    "id": 948002,
    "meaning": "Jehovah is the ultimate God",
    "name": "ellice",
    "origin": "Hebrew",
    "religion": "Christianity",
    "soundUrl": "https://cdn2.momjunction.com/wp-content/uploads/baby-names/audio_files/ellice-english.mp3"
  },
  {
    "gender": "Girl",
    "id": 948011,
    "meaning": "Blissful God provides salvation",
    "name": "ellicia",
    "origin": "Greek,Hebrew",
    "religion": "Christianity",
    "soundUrl": "https://cdn2.momjunction.com/wp-content/uploads/baby-names/audio_files/ellicia-english.mp3"
  },
  {
    "gender": "Girl",
    "id": 948021,
    "meaning": "God is my light",
    "name": "ellie",
    "origin": "German,Hebrew",
    "religion": "Christianity",
    "soundUrl": "https://cdn2.momjunction.com/wp-content/uploads/baby-names/audio_files/ellie-german.mp3"
  },
  {
    "gender": "Girl",
    "id": 948036,
    "meaning": "An answer to God\u0027s prayers",
    "name": "ellieana",
    "origin": "Hebrew",
    "religion": "Christianity",
    "soundUrl": "https://cdn2.momjunction.com/wp-content/uploads/baby-names/audio_files/ellieana-english.mp3"
  },
  {
    "gender": "Girl",
    "id": 948047,
    "meaning": "Jehovah is the God almighty",
    "name": "elliette",
    "origin": "Hebrew",
    "religion": "Christianity",
    "soundUrl": "https://cdn2.momjunction.com/wp-content/uploads/baby-names/audio_files/elliette-english.mp3"
  },
  {
    "gender": "Girl",
    "id": 948054,
    "meaning": "One who cannot be defeated",
    "name": "ellika",
    "origin": "Nordic",
    "religion": "Christianity",
    "soundUrl": "https://cdn2.momjunction.com/wp-content/uploads/baby-names/audio_files/ellika-english.mp3"
  },
  {
    "gender": "Girl",
    "id": 948060,
    "meaning": "The soothing ray of Sun; foreign element",
    "name": "ellin",
    "origin": "Greek",
    "religion": "Christianity",
    "soundUrl": "https://cdn2.momjunction.com/wp-content/uploads/baby-names/audio_files/ellin-english.mp3"
  },
  {
    "gender": "Girl",
    "id": 948073,
    "meaning": "The entire world; the bright and shining one",
    "name": "ellina",
    "origin": "German,Greek",
    "religion": "Christianity",
    "soundUrl": "https://cdn2.momjunction.com/wp-content/uploads/baby-names/audio_files/ellina-german.mp3"
  },
  {
    "gender": "Girl",
    "id": 948089,
    "meaning": "A generous person; A torch",
    "name": "ellinette",
    "origin": "Greek",
    "religion": "Christianity",
    "soundUrl": "https://cdn2.momjunction.com/wp-content/uploads/baby-names/audio_files/ellinette-english.mp3"
  },
  {
    "gender": "Girl",
    "id": 948105,
    "meaning": "One who is filled with bright daylight",
    "name": "ellinor",
    "origin": "French",
    "religion": "Christianity",
    "soundUrl": "https://cdn2.momjunction.com/wp-content/uploads/baby-names/audio_files/ellinor-english.mp3"
  },
  {
    "gender": "Girl",
    "id": 948120,
    "meaning": "One who considers Jehovah as God",
    "name": "ellinore",
    "origin": "Greek",
    "religion": "Christianity",
    "soundUrl": "https://cdn2.momjunction.com/wp-content/uploads/baby-names/audio_files/ellinore-english.mp3"
  },
  {
    "gender": "Girl",
    "id": 948151,
    "meaning": "My God is Yahweh",
    "name": "elliotte",
    "origin": "Greek",
    "religion": "Christianity",
    "soundUrl": "https://cdn2.momjunction.com/wp-content/uploads/baby-names/audio_files/elliotte-english.mp3"
  },
  {
    "gender": "Girl",
    "id": 948176,
    "meaning": "A Greek form of Elijah",
    "name": "ellisha",
    "origin": "English",
    "religion": "Christianity",
    "soundUrl": "https://cdn2.momjunction.com/wp-content/uploads/baby-names/audio_files/ellisha-english.mp3"
  },
  {
    "gender": "Girl",
    "id": 948187,
    "meaning": "God provides salvation and peace; blessed isles",
    "name": "ellisia",
    "origin": "Greek",
    "religion": "Christianity",
    "soundUrl": "https://cdn2.momjunction.com/wp-content/uploads/baby-names/audio_files/ellisia-english.mp3"
  },
  {
    "gender": "Girl",
    "id": 997065,
    "meaning": "Consecrated to God",
    "name": "Ellisif",
    "origin": "Norse,Norwegian",
    "religion": "Christianity",
    "soundUrl": "https://cdn2.momjunction.com/wp-content/uploads/baby-names/audio_files/Ellisif-english.mp3"
  },
  {
    "gender": "Girl",
    "id": 948206,
    "meaning": "One who provides satisfaction and comfort",
    "name": "ellissa",
    "origin": "Greek",
    "religion": "Christianity",
    "soundUrl": "https://cdn2.momjunction.com/wp-content/uploads/baby-names/audio_files/ellissa-english.mp3"
  },
  {
    "gender": "Girl",
    "id": 948231,
    "meaning": "Name of a color; Over-sensitive nature",
    "name": "elliw",
    "origin": "Welsh",
    "religion": "Christianity",
    "soundUrl": "https://cdn2.momjunction.com/wp-content/uploads/baby-names/audio_files/elliw-english.mp3"
  },
  {
    "gender": "Girl",
    "id": 948235,
    "meaning": "God provides protection; an apple",
    "name": "ellma",
    "origin": "Arabic",
    "religion": "",
    "soundUrl": "https://cdn2.momjunction.com/wp-content/uploads/baby-names/audio_files/ellma-arabic.mp3"
  },
  {
    "gender": "Girl",
    "id": 948237,
    "meaning": "One who is like an aristrocratic lady",
    "name": "ellmeera",
    "origin": "Arabic",
    "religion": "Christianity",
    "soundUrl": "https://cdn2.momjunction.com/wp-content/uploads/baby-names/audio_files/ellmeera-arabic.mp3"
  },
  {
    "gender": "Girl",
    "id": 948246,
    "meaning": "An aristrocratic lady",
    "name": "ellmera",
    "origin": "Arabic",
    "religion": "Christianity",
    "soundUrl": "https://cdn2.momjunction.com/wp-content/uploads/baby-names/audio_files/ellmera-arabic.mp3"
  },
  {
    "gender": "Girl",
    "id": 948250,
    "meaning": "One who is like an aristrocratic lady or a Princess",
    "name": "ellmeria",
    "origin": "Arabic",
    "religion": "Christianity",
    "soundUrl": "https://cdn2.momjunction.com/wp-content/uploads/baby-names/audio_files/ellmeria-arabic.mp3"
  },
  {
    "gender": "Girl",
    "id": 948252,
    "meaning": "One who is famous in war",
    "name": "ellois",
    "origin": "French,Teutonic",
    "religion": "Christianity",
    "soundUrl": "https://cdn2.momjunction.com/wp-content/uploads/baby-names/audio_files/ellois-english.mp3"
  },
  {
    "gender": "Girl",
    "id": 948254,
    "meaning": "One who is famous in a war",
    "name": "elloise",
    "origin": "French",
    "religion": "Christianity",
    "soundUrl": "https://cdn2.momjunction.com/wp-content/uploads/baby-names/audio_files/elloise-english.mp3"
  },
  {
    "gender": "Girl",
    "id": 948266,
    "meaning": "One who is passionate and loves freedom; Bright",
    "name": "ellon",
    "origin": "Greek",
    "religion": "Christianity",
    "soundUrl": "https://cdn2.momjunction.com/wp-content/uploads/baby-names/audio_files/ellon-english.mp3"
  },
  {
    "gender": "Girl",
    "id": 922605,
    "meaning": "Clouds; Name for cave temples in India",
    "name": "Ellora",
    "origin": "Indian",
    "religion": "",
    "soundUrl": "https://cdn2.momjunction.com/wp-content/uploads/baby-names/audio_files/Ellora-hindi.mp3"
  },
  {
    "gender": "Girl",
    "id": 948270,
    "meaning": "Salvation provider",
    "name": "ellorie",
    "origin": "English",
    "religion": "Christianity",
    "soundUrl": "https://cdn2.momjunction.com/wp-content/uploads/baby-names/audio_files/ellorie-english.mp3"
  },
  {
    "gender": "Girl",
    "id": 948281,
    "meaning": "One who is filled with joy and hapiness",
    "name": "ellory",
    "origin": "English",
    "religion": "Christianity",
    "soundUrl": "https://cdn2.momjunction.com/wp-content/uploads/baby-names/audio_files/ellory-english.mp3"
  },
  {
    "gender": "Girl",
    "id": 948289,
    "meaning": "One who is blessed with charming nature",
    "name": "ellot",
    "origin": "English",
    "religion": "Christianity",
    "soundUrl": "https://cdn2.momjunction.com/wp-content/uploads/baby-names/audio_files/ellot-english.mp3"
  },
  {
    "gender": "Girl",
    "id": 948294,
    "meaning": "An easy going and social person",
    "name": "ellota",
    "origin": "English",
    "religion": "Christianity",
    "soundUrl": "https://cdn2.momjunction.com/wp-content/uploads/baby-names/audio_files/ellota-english.mp3"
  },
  {
    "gender": "Girl",
    "id": 948299,
    "meaning": "One who is the source of creation",
    "name": "ellowyn",
    "origin": "English",
    "religion": "Christianity",
    "soundUrl": "https://cdn2.momjunction.com/wp-content/uploads/baby-names/audio_files/ellowyn-english.mp3"
  },
  {
    "gender": "Girl",
    "id": 948306,
    "meaning": "Exalted; God acts as an oath",
    "name": "ellsa",
    "origin": "German",
    "religion": "Christianity",
    "soundUrl": "https://cdn2.momjunction.com/wp-content/uploads/baby-names/audio_files/ellsa-german.mp3"
  },
  {
    "gender": "Girl",
    "id": 948350,
    "meaning": "My God is an oath",
    "name": "elly",
    "origin": "Irish",
    "religion": "Christianity",
    "soundUrl": "https://cdn2.momjunction.com/wp-content/uploads/baby-names/audio_files/elly-english.mp3"
  },
  {
    "gender": "Girl",
    "id": 948362,
    "meaning": "Compassionate; Greek form of Elijah",
    "name": "ellyce",
    "origin": "English",
    "religion": "Christianity",
    "soundUrl": "https://cdn2.momjunction.com/wp-content/uploads/baby-names/audio_files/ellyce-english.mp3"
  },
  {
    "gender": "Girl",
    "id": 948369,
    "meaning": "The one with creative and restless nature",
    "name": "ellyda",
    "origin": "English",
    "religion": "Christianity",
    "soundUrl": "https://cdn2.momjunction.com/wp-content/uploads/baby-names/audio_files/ellyda-english.mp3"
  },
  {
    "gender": "Girl",
    "id": 948372,
    "meaning": "Like Helen; a beautiful woman",
    "name": "ellyn",
    "origin": "English",
    "religion": "Christianity",
    "soundUrl": "https://cdn2.momjunction.com/wp-content/uploads/baby-names/audio_files/ellyn-english.mp3"
  },
  {
    "gender": "Girl",
    "id": 948376,
    "meaning": "An individual who likes harmony",
    "name": "ellyse",
    "origin": "English,Greek",
    "religion": "Christianity",
    "soundUrl": "https://cdn2.momjunction.com/wp-content/uploads/baby-names/audio_files/ellyse-english.mp3"
  },
  {
    "gender": "Girl",
    "id": 948387,
    "meaning": "A reason; one who is from heaven",
    "name": "ellysia",
    "origin": "English",
    "religion": "Christianity",
    "soundUrl": "https://cdn2.momjunction.com/wp-content/uploads/baby-names/audio_files/ellysia-english.mp3"
  },
  {
    "gender": "Girl",
    "id": 948400,
    "meaning": "The one who is Ellis\u0027s son",
    "name": "ellyson",
    "origin": "English",
    "religion": "Christianity",
    "soundUrl": "https://cdn2.momjunction.com/wp-content/uploads/baby-names/audio_files/ellyson-english.mp3"
  },
  {
    "gender": "Girl",
    "id": 948416,
    "meaning": "One who is sweet like an apple",
    "name": "elma",
    "origin": "Arabic,German",
    "religion": "",
    "soundUrl": "https://cdn2.momjunction.com/wp-content/uploads/baby-names/audio_files/elma-arabic.mp3"
  },
  {
    "gender": "Girl",
    "id": 998173,
    "meaning": "One who is devoted to faith or civilized; A variant of Almedina",
    "name": "Elmedina",
    "origin": "Arabic,Bosnian",
    "religion": "Islam",
    "soundUrl": "https://cdn2.momjunction.com/wp-content/uploads/baby-names/audio_files/Elmedina-arabic.mp3"
  },
  {
    "gender": "Girl",
    "id": 948448,
    "meaning": "One who has an intimidating fame; A helmet",
    "name": "elmeena",
    "origin": "German",
    "religion": "Christianity",
    "soundUrl": "https://cdn2.momjunction.com/wp-content/uploads/baby-names/audio_files/elmeena-german.mp3"
  },
  {
    "gender": "Girl",
    "id": 948454,
    "meaning": "A noble Princess",
    "name": "elmeera",
    "origin": "Arabic",
    "religion": "",
    "soundUrl": "https://cdn2.momjunction.com/wp-content/uploads/baby-names/audio_files/elmeera-arabic.mp3"
  },
  {
    "gender": "Girl",
    "id": 948456,
    "meaning": "A beautiful and aristrocratic lady",
    "name": "elmeeria",
    "origin": "Arabic",
    "religion": "Christianity",
    "soundUrl": "https://cdn2.momjunction.com/wp-content/uploads/baby-names/audio_files/elmeeria-arabic.mp3"
  },
  {
    "gender": "Girl",
    "id": 948459,
    "meaning": "A ady with an indimidating fame",
    "name": "elmena",
    "origin": "Teutonic",
    "religion": "Christianity",
    "soundUrl": "https://cdn2.momjunction.com/wp-content/uploads/baby-names/audio_files/elmena-english.mp3"
  },
  {
    "gender": "Girl",
    "id": 948471,
    "meaning": "One who excels; Likeable person",
    "name": "elmera",
    "origin": "English",
    "religion": "Christianity",
    "soundUrl": "https://cdn2.momjunction.com/wp-content/uploads/baby-names/audio_files/elmera-english.mp3"
  },
  {
    "gender": "Girl",
    "id": 948478,
    "meaning": "One who is social, likable and friendly",
    "name": "elmeria",
    "origin": "English",
    "religion": "Christianity",
    "soundUrl": "https://cdn2.momjunction.com/wp-content/uploads/baby-names/audio_files/elmeria-english.mp3"
  },
  {
    "gender": "Girl",
    "id": 948482,
    "meaning": "One who has a noble heart",
    "name": "elmerya",
    "origin": "Arabic",
    "religion": "",
    "soundUrl": "https://cdn2.momjunction.com/wp-content/uploads/baby-names/audio_files/elmerya-arabic.mp3"
  },
  {
    "gender": "Girl",
    "id": 948488,
    "meaning": "Intimidating and famous person",
    "name": "elmina",
    "origin": "Teutonic",
    "religion": "Christianity",
    "soundUrl": "https://cdn2.momjunction.com/wp-content/uploads/baby-names/audio_files/elmina-english.mp3"
  },
  {
    "gender": "Girl",
    "id": 948501,
    "meaning": "Noble and kind hearted person; A born princess",
    "name": "elmira",
    "origin": "English",
    "religion": "Christianity",
    "soundUrl": "https://cdn2.momjunction.com/wp-content/uploads/baby-names/audio_files/elmira-english.mp3"
  },
  {
    "gender": "Girl",
    "id": 948539,
    "meaning": "An imaginative and idealistic person; Noble",
    "name": "elmyra",
    "origin": "English",
    "religion": "Christianity",
    "soundUrl": "https://cdn2.momjunction.com/wp-content/uploads/baby-names/audio_files/elmyra-english.mp3"
  },
  {
    "gender": "Girl",
    "id": 948557,
    "meaning": "A wise aristrocratic lady",
    "name": "elmyrah",
    "origin": "Arabic",
    "religion": "",
    "soundUrl": "https://cdn2.momjunction.com/wp-content/uploads/baby-names/audio_files/elmyrah-arabic.mp3"
  },
  {
    "gender": "Girl",
    "id": 948561,
    "meaning": "A creative person",
    "name": "elna",
    "origin": "Greek,Scandinavian",
    "religion": "Christianity",
    "soundUrl": "https://cdn2.momjunction.com/wp-content/uploads/baby-names/audio_files/elna-english.mp3"
  },
  {
    "gender": "Girl",
    "id": 1000449,
    "meaning": "People; Country; Nation",
    "name": "Elnara",
    "origin": "Kazakh,Turkish",
    "religion": "Islam",
    "soundUrl": "https://cdn2.momjunction.com/wp-content/uploads/baby-names/audio_files/Elnara-english.mp3"
  },
  {
    "gender": "Girl",
    "id": 948575,
    "meaning": "One who is born to spread light",
    "name": "elnora",
    "origin": "English",
    "religion": "Christianity",
    "soundUrl": "https://cdn2.momjunction.com/wp-content/uploads/baby-names/audio_files/elnora-english.mp3"
  },
  {
    "gender": "Girl",
    "id": 991561,
    "meaning": "Goddess in Brazilian language",
    "name": "Eloa",
    "origin": "Brazilian",
    "religion": "Christianity",
    "soundUrl": "https://cdn2.momjunction.com/wp-content/uploads/baby-names/audio_files/Eloa-english.mp3"
  },
  {
    "gender": "Girl",
    "id": 948582,
    "meaning": "Foreign wealth",
    "name": "elodia",
    "origin": "Spanish",
    "religion": "Christianity",
    "soundUrl": "https://cdn2.momjunction.com/wp-content/uploads/baby-names/audio_files/elodia-english.mp3"
  },
  {
    "gender": "Girl",
    "id": 948595,
    "meaning": "All wealth",
    "name": "elodie",
    "origin": "French",
    "religion": "Christianity",
    "soundUrl": "https://cdn2.momjunction.com/wp-content/uploads/baby-names/audio_files/elodie-english.mp3"
  },
  {
    "gender": "Girl",
    "id": 948628,
    "meaning": "Healthy; Wide",
    "name": "eloisa",
    "origin": "French,Italian,Spanish",
    "religion": "Christianity",
    "soundUrl": "https://cdn2.momjunction.com/wp-content/uploads/baby-names/audio_files/eloisa-english.mp3"
  },
  {
    "gender": "Girl",
    "id": 948639,
    "meaning": "Famous warrior",
    "name": "eloise",
    "origin": "French,German",
    "religion": "Christianity",
    "soundUrl": "https://cdn2.momjunction.com/wp-content/uploads/baby-names/audio_files/eloise-english.mp3"
  },
  {
    "gender": "Girl",
    "id": 989086,
    "meaning": "A beautiful woman; Jewel",
    "name": "Elok",
    "origin": "Indonesian",
    "religion": "",
    "soundUrl": "https://cdn2.momjunction.com/wp-content/uploads/baby-names/audio_files/Elok-english.mp3"
  },
  {
    "gender": "Girl",
    "id": 948649,
    "meaning": "A healthy and wise individual; Wide one",
    "name": "Elom",
    "origin": "German",
    "religion": "Christianity",
    "soundUrl": "https://cdn2.momjunction.com/wp-content/uploads/baby-names/audio_files/Elom-german.mp3"
  },
  {
    "gender": "Girl",
    "id": 948672,
    "meaning": "An individual who is like an oak tree; The bright one",
    "name": "elonso",
    "origin": "Greek",
    "religion": "Christianity",
    "soundUrl": "https://cdn2.momjunction.com/wp-content/uploads/baby-names/audio_files/elonso-english.mp3"
  }
]