[
  {
    "gender": "Boy",
    "id": 990645,
    "meaning": "You won’t follow my lead",
    "name": "Ebhaleleme",
    "origin": "Nigerian",
    "religion": "",
    "soundUrl": "https://cdn2.momjunction.com/wp-content/uploads/baby-names/audio_files/Ebhaleleme-english.mp3"
  },
  {
    "gender": "Boy",
    "id": 922450,
    "meaning": "One of many names of Ganpati signifying his elephant face",
    "name": "Ebhanan",
    "origin": "Indian",
    "religion": "",
    "soundUrl": "https://cdn2.momjunction.com/wp-content/uploads/baby-names/audio_files/Ebhanan-hindi.mp3"
  },
  {
    "gender": "Boy",
    "id": 922451,
    "meaning": "Paternal; A variant of name Eby",
    "name": "Ebi",
    "origin": "Persian",
    "religion": "",
    "soundUrl": "https://cdn2.momjunction.com/wp-content/uploads/baby-names/audio_files/Ebi-english.mp3"
  },
  {
    "gender": "Boy",
    "id": 994803,
    "meaning": "One who is born on a Tuesday",
    "name": "Ebo",
    "origin": "Ghana",
    "religion": "",
    "soundUrl": "https://cdn2.momjunction.com/wp-content/uploads/baby-names/audio_files/Ebo-english.mp3"
  },
  {
    "gender": "Boy",
    "id": 945475,
    "meaning": "A very expressive; Adventurous and spontaneous nature person",
    "name": "eborard",
    "origin": "English",
    "religion": "Christianity",
    "soundUrl": "https://cdn2.momjunction.com/wp-content/uploads/baby-names/audio_files/eborard-english.mp3"
  },
  {
    "gender": "Boy",
    "id": 945478,
    "meaning": "Derived from the word Ibrahim it means God\u0027s messenger; Father of many nations",
    "name": "ebrahim",
    "origin": "Arabic",
    "religion": "Christianity",
    "soundUrl": "https://cdn2.momjunction.com/wp-content/uploads/baby-names/audio_files/ebrahim-arabic.mp3"
  },
  {
    "gender": "Boy",
    "id": 945479,
    "meaning": "The one who gives strong advice; One who is a powerful counselor",
    "name": "ebrard",
    "origin": "Hebrew",
    "religion": "Christianity",
    "soundUrl": "https://cdn2.momjunction.com/wp-content/uploads/baby-names/audio_files/ebrard-english.mp3"
  },
  {
    "gender": "Boy",
    "id": 996750,
    "meaning": "The glory and greatness of God",
    "name": "Ebubechukwu",
    "origin": "Igbo,Nigerian",
    "religion": "Christianity",
    "soundUrl": "https://cdn2.momjunction.com/wp-content/uploads/baby-names/audio_files/Ebubechukwu-english.mp3"
  },
  {
    "gender": "Boy",
    "id": 945482,
    "meaning": "A secretive person; one who is like Bull",
    "name": "ebull",
    "origin": "English",
    "religion": "Christianity",
    "soundUrl": "https://cdn2.momjunction.com/wp-content/uploads/baby-names/audio_files/ebull-english.mp3"
  },
  {
    "gender": "Boy",
    "id": 945483,
    "meaning": "member of a good counsel",
    "name": "ebulus",
    "origin": "English",
    "religion": "Christianity",
    "soundUrl": "https://cdn2.momjunction.com/wp-content/uploads/baby-names/audio_files/ebulus-english.mp3"
  },
  {
    "gender": "Boy",
    "id": 945484,
    "meaning": "One who is strong as a wild boar",
    "name": "eburhard",
    "origin": "Old German",
    "religion": "Christianity",
    "soundUrl": "https://cdn2.momjunction.com/wp-content/uploads/baby-names/audio_files/eburhard-german.mp3"
  },
  {
    "gender": "Boy",
    "id": 945485,
    "meaning": "An inspirational saying for being strong; has Boar strength",
    "name": "eburhardt",
    "origin": "German",
    "religion": "Christianity",
    "soundUrl": "https://cdn2.momjunction.com/wp-content/uploads/baby-names/audio_files/eburhardt-german.mp3"
  },
  {
    "gender": "Boy",
    "id": 922452,
    "meaning": "Wanted; Desired; Wished; Craved; Longed; Aspired; Yearned",
    "name": "Ecchit",
    "origin": "Indian",
    "religion": "",
    "soundUrl": "https://cdn2.momjunction.com/wp-content/uploads/baby-names/audio_files/Ecchit-hindi.mp3"
  },
  {
    "gender": "Boy",
    "id": 922453,
    "meaning": "A King; Ruler; Emperor; Leader",
    "name": "Ecchvaku",
    "origin": "Indian",
    "religion": "",
    "soundUrl": "https://cdn2.momjunction.com/wp-content/uploads/baby-names/audio_files/Ecchvaku-hindi.mp3"
  },
  {
    "gender": "Boy",
    "id": 945490,
    "meaning": "Emotional person who is energized",
    "name": "ecci",
    "origin": "English",
    "religion": "Christianity",
    "soundUrl": "https://cdn2.momjunction.com/wp-content/uploads/baby-names/audio_files/ecci-english.mp3"
  },
  {
    "gender": "Boy",
    "id": 945492,
    "meaning": "An emotional; Clever and good individual",
    "name": "ecga",
    "origin": "English",
    "religion": "Christianity",
    "soundUrl": "https://cdn2.momjunction.com/wp-content/uploads/baby-names/audio_files/ecga-english.mp3"
  },
  {
    "gender": "Boy",
    "id": 945493,
    "meaning": "A brave friend; they are clever minded",
    "name": "ecgbald",
    "origin": "English",
    "religion": "Christianity",
    "soundUrl": "https://cdn2.momjunction.com/wp-content/uploads/baby-names/audio_files/ecgbald-english.mp3"
  },
  {
    "gender": "Boy",
    "id": 945494,
    "meaning": "Has analytical mind and is bright and shiny",
    "name": "ecgbehrt",
    "origin": "English",
    "religion": "Christianity",
    "soundUrl": "https://cdn2.momjunction.com/wp-content/uploads/baby-names/audio_files/ecgbehrt-english.mp3"
  },
  {
    "gender": "Boy",
    "id": 945495,
    "meaning": "One who has high level of understanding; quick thinker and intelligent",
    "name": "ecgbeorht",
    "origin": "English",
    "religion": "Christianity",
    "soundUrl": "https://cdn2.momjunction.com/wp-content/uploads/baby-names/audio_files/ecgbeorht-english.mp3"
  },
  {
    "gender": "Boy",
    "id": 945496,
    "meaning": "A sharp edge of a sword",
    "name": "ecgbert",
    "origin": "Anglo Saxon",
    "religion": "Christianity",
    "soundUrl": "https://cdn2.momjunction.com/wp-content/uploads/baby-names/audio_files/ecgbert-english.mp3"
  },
  {
    "gender": "Boy",
    "id": 945497,
    "meaning": "One who is born with a friendly nature",
    "name": "ecgel",
    "origin": "English",
    "religion": "Christianity",
    "soundUrl": "https://cdn2.momjunction.com/wp-content/uploads/baby-names/audio_files/ecgel-english.mp3"
  },
  {
    "gender": "Boy",
    "id": 945498,
    "meaning": "A born leader; name of a king",
    "name": "ecgfrith",
    "origin": "Anglo Saxon",
    "religion": "Christianity",
    "soundUrl": "https://cdn2.momjunction.com/wp-content/uploads/baby-names/audio_files/ecgfrith-english.mp3"
  },
  {
    "gender": "Boy",
    "id": 945499,
    "meaning": "A clever person; who is sharp witted",
    "name": "ecgheard",
    "origin": "English",
    "religion": "Christianity",
    "soundUrl": "https://cdn2.momjunction.com/wp-content/uploads/baby-names/audio_files/ecgheard-english.mp3"
  },
  {
    "gender": "Boy",
    "id": 945500,
    "meaning": "One who is clever and makes decisions at right time",
    "name": "ecghere",
    "origin": "English",
    "religion": "Christianity",
    "soundUrl": "https://cdn2.momjunction.com/wp-content/uploads/baby-names/audio_files/ecghere-english.mp3"
  },
  {
    "gender": "Boy",
    "id": 945501,
    "meaning": "A stable; Warm and motherly being",
    "name": "ecgi",
    "origin": "English",
    "religion": "Christianity",
    "soundUrl": "https://cdn2.momjunction.com/wp-content/uploads/baby-names/audio_files/ecgi-english.mp3"
  },
  {
    "gender": "Boy",
    "id": 945502,
    "meaning": "Strong protector; one who is thoughtful and systematic",
    "name": "ecgmund",
    "origin": "German",
    "religion": "Christianity",
    "soundUrl": "https://cdn2.momjunction.com/wp-content/uploads/baby-names/audio_files/ecgmund-german.mp3"
  },
  {
    "gender": "Boy",
    "id": 945503,
    "meaning": "Alert; one who is thoughtful",
    "name": "ecgred",
    "origin": "Greek",
    "religion": "Christianity",
    "soundUrl": "https://cdn2.momjunction.com/wp-content/uploads/baby-names/audio_files/ecgred-english.mp3"
  },
  {
    "gender": "Boy",
    "id": 945504,
    "meaning": "Loud as a thunder; having strong desire to succeed",
    "name": "ecgric",
    "origin": "English",
    "religion": "Christianity",
    "soundUrl": "https://cdn2.momjunction.com/wp-content/uploads/baby-names/audio_files/ecgric-english.mp3"
  },
  {
    "gender": "Boy",
    "id": 945506,
    "meaning": "Brought up by nature or in the environment of forest; ruler of law",
    "name": "ecgwald",
    "origin": "German",
    "religion": "Christianity",
    "soundUrl": "https://cdn2.momjunction.com/wp-content/uploads/baby-names/audio_files/ecgwald-german.mp3"
  },
  {
    "gender": "Boy",
    "id": 945507,
    "meaning": "One who is quick in actions; spontaneous and generous",
    "name": "ecgwine",
    "origin": "English",
    "religion": "Christianity",
    "soundUrl": "https://cdn2.momjunction.com/wp-content/uploads/baby-names/audio_files/ecgwine-english.mp3"
  },
  {
    "gender": "Boy",
    "id": 945508,
    "meaning": "A clever being; has extravagant nature",
    "name": "ecgwulf",
    "origin": "German",
    "religion": "Christianity",
    "soundUrl": "https://cdn2.momjunction.com/wp-content/uploads/baby-names/audio_files/ecgwulf-german.mp3"
  },
  {
    "gender": "Boy",
    "id": 996751,
    "meaning": "Don’t forget your God and your father",
    "name": "Echezonanna",
    "origin": "Igbo,Nigerian",
    "religion": "Christianity",
    "soundUrl": "https://cdn2.momjunction.com/wp-content/uploads/baby-names/audio_files/Echezonanna-english.mp3"
  },
  {
    "gender": "Boy",
    "id": 945513,
    "meaning": "One who is strong like a sword",
    "name": "eckard",
    "origin": "German",
    "religion": "Christianity",
    "soundUrl": "https://cdn2.momjunction.com/wp-content/uploads/baby-names/audio_files/eckard-german.mp3"
  },
  {
    "gender": "Boy",
    "id": 945514,
    "meaning": "A brave; edge point",
    "name": "eckardt",
    "origin": "German",
    "religion": "Christianity",
    "soundUrl": "https://cdn2.momjunction.com/wp-content/uploads/baby-names/audio_files/eckardt-german.mp3"
  },
  {
    "gender": "Boy",
    "id": 945515,
    "meaning": "An edge; one who is powerful and brave",
    "name": "eckart",
    "origin": "German",
    "religion": "Christianity",
    "soundUrl": "https://cdn2.momjunction.com/wp-content/uploads/baby-names/audio_files/eckart-german.mp3"
  },
  {
    "gender": "Boy",
    "id": 945516,
    "meaning": "A bright sword; shiny metal or weapon",
    "name": "eckbert",
    "origin": "German",
    "religion": "Christianity",
    "soundUrl": "https://cdn2.momjunction.com/wp-content/uploads/baby-names/audio_files/eckbert-german.mp3"
  },
  {
    "gender": "Boy",
    "id": 945517,
    "meaning": "An edge or corner of any space",
    "name": "ecke",
    "origin": "German",
    "religion": "Christianity",
    "soundUrl": "https://cdn2.momjunction.com/wp-content/uploads/baby-names/audio_files/ecke-german.mp3"
  },
  {
    "gender": "Boy",
    "id": 945518,
    "meaning": "A German saying to motivate means be strong through the sword",
    "name": "eckehard",
    "origin": "German",
    "religion": "Christianity",
    "soundUrl": "https://cdn2.momjunction.com/wp-content/uploads/baby-names/audio_files/eckehard-german.mp3"
  },
  {
    "gender": "Boy",
    "id": 945519,
    "meaning": "A corner or a hidden edge",
    "name": "eckehardt",
    "origin": "German",
    "religion": "Christianity",
    "soundUrl": "https://cdn2.momjunction.com/wp-content/uploads/baby-names/audio_files/eckehardt-german.mp3"
  },
  {
    "gender": "Boy",
    "id": 945520,
    "meaning": "Strong; deer a scared one",
    "name": "eckehart",
    "origin": "Teutonic",
    "religion": "Christianity",
    "soundUrl": "https://cdn2.momjunction.com/wp-content/uploads/baby-names/audio_files/eckehart-english.mp3"
  },
  {
    "gender": "Boy",
    "id": 945521,
    "meaning": "One who is sacred and connected with god",
    "name": "eckerd",
    "origin": "German",
    "religion": "Christianity",
    "soundUrl": "https://cdn2.momjunction.com/wp-content/uploads/baby-names/audio_files/eckerd-german.mp3"
  },
  {
    "gender": "Boy",
    "id": 945522,
    "meaning": "Strong and pointed as brave",
    "name": "eckert",
    "origin": "German",
    "religion": "Christianity",
    "soundUrl": "https://cdn2.momjunction.com/wp-content/uploads/baby-names/audio_files/eckert-german.mp3"
  },
  {
    "gender": "Boy",
    "id": 945523,
    "meaning": "Strong as sword and sharp as a sword\u0027s edge",
    "name": "eckhard",
    "origin": "German",
    "religion": "Christianity",
    "soundUrl": "https://cdn2.momjunction.com/wp-content/uploads/baby-names/audio_files/eckhard-german.mp3"
  },
  {
    "gender": "Boy",
    "id": 945524,
    "meaning": "A pointed edge; brave and strong",
    "name": "eckhardt",
    "origin": "German",
    "religion": "Christianity",
    "soundUrl": "https://cdn2.momjunction.com/wp-content/uploads/baby-names/audio_files/eckhardt-german.mp3"
  },
  {
    "gender": "Boy",
    "id": 945525,
    "meaning": "To keep on point that is able to cut or pierce",
    "name": "eckhart",
    "origin": "German",
    "religion": "Christianity",
    "soundUrl": "https://cdn2.momjunction.com/wp-content/uploads/baby-names/audio_files/eckhart-german.mp3"
  },
  {
    "gender": "Boy",
    "id": 945526,
    "meaning": "the only winner or victorious; who always succeed",
    "name": "eckjeet",
    "origin": "Indian",
    "religion": "Sikh",
    "soundUrl": "https://cdn2.momjunction.com/wp-content/uploads/baby-names/audio_files/eckjeet-hindi.mp3"
  },
  {
    "gender": "Boy",
    "id": 945527,
    "meaning": "Father of Arthur; to hold; keep under control or within the limits",
    "name": "ector",
    "origin": "Greek",
    "religion": "Christianity",
    "soundUrl": "https://cdn2.momjunction.com/wp-content/uploads/baby-names/audio_files/ector-english.mp3"
  },
  {
    "gender": "Boy",
    "id": 945528,
    "meaning": "To restrain; One who has imaginative and creative mind",
    "name": "ectorius",
    "origin": "Roman",
    "religion": "Christianity",
    "soundUrl": "https://cdn2.momjunction.com/wp-content/uploads/baby-names/audio_files/ectorius-english.mp3"
  },
  {
    "gender": "Boy",
    "id": 945529,
    "meaning": "A prosperous or wealthy guard who provides protection",
    "name": "ed",
    "origin": "French",
    "religion": "Christianity",
    "soundUrl": "https://cdn2.momjunction.com/wp-content/uploads/baby-names/audio_files/ed-english.mp3"
  },
  {
    "gender": "Boy",
    "id": 922454,
    "meaning": "God; Supreme Being; Creator and Protector of this universe",
    "name": "Edadeha",
    "origin": "Indian",
    "religion": "",
    "soundUrl": "https://cdn2.momjunction.com/wp-content/uploads/baby-names/audio_files/Edadeha-hindi.mp3"
  },
  {
    "gender": "Boy",
    "id": 1000528,
    "meaning": "The rich have good destiny",
    "name": "Edaferierhi",
    "origin": "Nigerian,Urhobo",
    "religion": "Christianity",
    "soundUrl": "https://cdn2.momjunction.com/wp-content/uploads/baby-names/audio_files/Edaferierhi-english.mp3"
  },
  {
    "gender": "Boy",
    "id": 1000529,
    "meaning": "The wealthy have spoken",
    "name": "Edafetanure",
    "origin": "Nigerian,Urhobo",
    "religion": "Christianity",
    "soundUrl": "https://cdn2.momjunction.com/wp-content/uploads/baby-names/audio_files/Edafetanure-english.mp3"
  },
  {
    "gender": "Boy",
    "id": 945533,
    "meaning": "Little fire; Fiery one",
    "name": "edan",
    "origin": "Scottish",
    "religion": "Christianity",
    "soundUrl": "https://cdn2.momjunction.com/wp-content/uploads/baby-names/audio_files/edan-english.mp3"
  },
  {
    "gender": "Boy",
    "id": 945535,
    "meaning": "One who is a born wealthy; bright person",
    "name": "edbert",
    "origin": "English",
    "religion": "Christianity",
    "soundUrl": "https://cdn2.momjunction.com/wp-content/uploads/baby-names/audio_files/edbert-english.mp3"
  },
  {
    "gender": "Boy",
    "id": 945536,
    "meaning": "A prosperous administrator",
    "name": "edborough",
    "origin": "Scottish",
    "religion": "Christianity",
    "soundUrl": "https://cdn2.momjunction.com/wp-content/uploads/baby-names/audio_files/edborough-english.mp3"
  },
  {
    "gender": "Boy",
    "id": 945537,
    "meaning": "The great; Guardian protector",
    "name": "edburga",
    "origin": "Anglo Saxon",
    "religion": "Christianity",
    "soundUrl": "https://cdn2.momjunction.com/wp-content/uploads/baby-names/audio_files/edburga-english.mp3"
  },
  {
    "gender": "Boy",
    "id": 945538,
    "meaning": "A royal; Prosperous; Guardian of wealth",
    "name": "edd",
    "origin": "Old English",
    "religion": "Christianity",
    "soundUrl": "https://cdn2.momjunction.com/wp-content/uploads/baby-names/audio_files/edd-english.mp3"
  },
  {
    "gender": "Boy",
    "id": 945540,
    "meaning": "One who is wealthy; Swedish form of eddie",
    "name": "edde",
    "origin": "British",
    "religion": "Christianity",
    "soundUrl": "https://cdn2.momjunction.com/wp-content/uploads/baby-names/audio_files/edde-english.mp3"
  },
  {
    "gender": "Boy",
    "id": 945543,
    "meaning": "One who is rich in friendship; a Wealthy protector",
    "name": "eddie",
    "origin": "French",
    "religion": "Christianity",
    "soundUrl": "https://cdn2.momjunction.com/wp-content/uploads/baby-names/audio_files/eddie-english.mp3"
  },
  {
    "gender": "Boy",
    "id": 945544,
    "meaning": "Brave and powerful son of Edward",
    "name": "eddis",
    "origin": "English",
    "religion": "Christianity",
    "soundUrl": "https://cdn2.momjunction.com/wp-content/uploads/baby-names/audio_files/eddis-english.mp3"
  },
  {
    "gender": "Boy",
    "id": 945545,
    "meaning": "A successor of wealth; Ed\u0027s son",
    "name": "eddison",
    "origin": "Anglo Saxon",
    "religion": "Christianity",
    "soundUrl": "https://cdn2.momjunction.com/wp-content/uploads/baby-names/audio_files/eddison-english.mp3"
  },
  {
    "gender": "Boy",
    "id": 945548,
    "meaning": "A good fortune; determine and stubborn",
    "name": "eddrick",
    "origin": "English",
    "religion": "Christianity",
    "soundUrl": "https://cdn2.momjunction.com/wp-content/uploads/baby-names/audio_files/eddrick-english.mp3"
  },
  {
    "gender": "Boy",
    "id": 945549,
    "meaning": "Strong in material sense and is idealistic",
    "name": "eddricus",
    "origin": "English",
    "religion": "Christianity",
    "soundUrl": "https://cdn2.momjunction.com/wp-content/uploads/baby-names/audio_files/eddricus-english.mp3"
  },
  {
    "gender": "Boy",
    "id": 945551,
    "meaning": "A wealthy guardian; Rich and friendly",
    "name": "eddy",
    "origin": "English",
    "religion": "Christianity",
    "soundUrl": "https://cdn2.momjunction.com/wp-content/uploads/baby-names/audio_files/eddy-english.mp3"
  },
  {
    "gender": "Boy",
    "id": 945557,
    "meaning": "A guardian of property; owner of many spears",
    "name": "edek",
    "origin": "Polish",
    "religion": "Christianity",
    "soundUrl": "https://cdn2.momjunction.com/wp-content/uploads/baby-names/audio_files/edek-english.mp3"
  },
  {
    "gender": "Boy",
    "id": 945559,
    "meaning": "The noble one who is also bravely hearted",
    "name": "edel",
    "origin": "German",
    "religion": "Christianity",
    "soundUrl": "https://cdn2.momjunction.com/wp-content/uploads/baby-names/audio_files/edel-german.mp3"
  },
  {
    "gender": "Boy",
    "id": 945560,
    "meaning": "Hardy; a noble and strong being",
    "name": "edelhard",
    "origin": "German",
    "religion": "Christianity",
    "soundUrl": "https://cdn2.momjunction.com/wp-content/uploads/baby-names/audio_files/edelhard-german.mp3"
  },
  {
    "gender": "Boy",
    "id": 945567,
    "meaning": "One who is having a high rank",
    "name": "edelmarr",
    "origin": "English",
    "religion": "Christianity",
    "soundUrl": "https://cdn2.momjunction.com/wp-content/uploads/baby-names/audio_files/edelmarr-english.mp3"
  },
  {
    "gender": "Boy",
    "id": 1000530,
    "meaning": "The day I did them a favor",
    "name": "Edemirukaye",
    "origin": "Nigerian,Urhobo",
    "religion": "Christianity",
    "soundUrl": "https://cdn2.momjunction.com/wp-content/uploads/baby-names/audio_files/Edemirukaye-english.mp3"
  },
  {
    "gender": "Boy",
    "id": 945577,
    "meaning": "A flock; group",
    "name": "eder",
    "origin": "Hebrew",
    "religion": "Christianity",
    "soundUrl": "https://cdn2.momjunction.com/wp-content/uploads/baby-names/audio_files/eder-english.mp3"
  },
  {
    "gender": "Boy",
    "id": 945578,
    "meaning": "The legendary son of Nudd",
    "name": "edern",
    "origin": "Welsh",
    "religion": "Christianity",
    "soundUrl": "https://cdn2.momjunction.com/wp-content/uploads/baby-names/audio_files/edern-english.mp3"
  },
  {
    "gender": "Boy",
    "id": 1000531,
    "meaning": "Sacred day of worship in traditional religion",
    "name": "Edewor",
    "origin": "Nigerian,Urhobo",
    "religion": "Christianity",
    "soundUrl": "https://cdn2.momjunction.com/wp-content/uploads/baby-names/audio_files/Edewor-english.mp3"
  },
  {
    "gender": "Boy",
    "id": 945581,
    "meaning": "Rich; Prosperous; Spear",
    "name": "edgar",
    "origin": "English",
    "religion": "Christianity",
    "soundUrl": "https://cdn2.momjunction.com/wp-content/uploads/baby-names/audio_files/edgar-english.mp3"
  },
  {
    "gender": "Boy",
    "id": 945582,
    "meaning": "A brave and strong spearman",
    "name": "edgard",
    "origin": "Anglo Saxon",
    "religion": "Christianity",
    "soundUrl": "https://cdn2.momjunction.com/wp-content/uploads/baby-names/audio_files/edgard-english.mp3"
  },
  {
    "gender": "Boy",
    "id": 945583,
    "meaning": "A wealthy man who is known for riches",
    "name": "edgardo",
    "origin": "Italian,Spanish",
    "religion": "Christianity",
    "soundUrl": "https://cdn2.momjunction.com/wp-content/uploads/baby-names/audio_files/edgardo-english.mp3"
  },
  {
    "gender": "Boy",
    "id": 996617,
    "meaning": "Latvia version of Edgar; Fortunate and powerful",
    "name": "Edgars",
    "origin": "English,Latvian",
    "religion": "Christianity",
    "soundUrl": "https://cdn2.momjunction.com/wp-content/uploads/baby-names/audio_files/Edgars-english.mp3"
  },
  {
    "gender": "Boy",
    "id": 988374,
    "meaning": "A prosperous warrior",
    "name": "Edgarton",
    "origin": "Belgian",
    "religion": "Christianity",
    "soundUrl": "https://cdn2.momjunction.com/wp-content/uploads/baby-names/audio_files/Edgarton-english.mp3"
  },
  {
    "gender": "Boy",
    "id": 945584,
    "meaning": "An end of surface; A trendsetter",
    "name": "edge",
    "origin": "United States",
    "religion": "Christianity",
    "soundUrl": "https://cdn2.momjunction.com/wp-content/uploads/baby-names/audio_files/edge-english.mp3"
  },
  {
    "gender": "Boy",
    "id": 945585,
    "meaning": "One who is cutting; sarcastic in nature",
    "name": "edged",
    "origin": "English",
    "religion": "Christianity",
    "soundUrl": "https://cdn2.momjunction.com/wp-content/uploads/baby-names/audio_files/edged-english.mp3"
  },
  {
    "gender": "Boy",
    "id": 987622,
    "meaning": "Wealthy spear or owner of many spears",
    "name": "Edgerin",
    "origin": "Jamaican",
    "religion": "",
    "soundUrl": "https://cdn2.momjunction.com/wp-content/uploads/baby-names/audio_files/Edgerin-english.mp3"
  },
  {
    "gender": "Boy",
    "id": 945586,
    "meaning": "Who has sharpness of a blade; border",
    "name": "edgert",
    "origin": "Anglo Saxon",
    "religion": "Christianity",
    "soundUrl": "https://cdn2.momjunction.com/wp-content/uploads/baby-names/audio_files/edgert-english.mp3"
  },
  {
    "gender": "Boy",
    "id": 945587,
    "meaning": "A blessed town; Prosperous warrior",
    "name": "edgerton",
    "origin": "English",
    "religion": "Christianity",
    "soundUrl": "https://cdn2.momjunction.com/wp-content/uploads/baby-names/audio_files/edgerton-english.mp3"
  },
  {
    "gender": "Boy",
    "id": 945591,
    "meaning": "One who is prosperous in war",
    "name": "edgyue",
    "origin": "English",
    "religion": "Christianity",
    "soundUrl": "https://cdn2.momjunction.com/wp-content/uploads/baby-names/audio_files/edgyue-english.mp3"
  },
  {
    "gender": "Boy",
    "id": 922455,
    "meaning": "Happiness; Delighted; Joyful; Glad; Rejoiced",
    "name": "Edhas",
    "origin": "Indian",
    "religion": "Hindu",
    "soundUrl": "https://cdn2.momjunction.com/wp-content/uploads/baby-names/audio_files/Edhas-hindi.mp3"
  },
  {
    "gender": "Boy",
    "id": 922456,
    "meaning": "Born of Wood; Fire; Happiness; Delight; Joyful",
    "name": "Edhatu",
    "origin": "Indian",
    "religion": "",
    "soundUrl": "https://cdn2.momjunction.com/wp-content/uploads/baby-names/audio_files/Edhatu-hindi.mp3"
  },
  {
    "gender": "Boy",
    "id": 998169,
    "meaning": "Dark-skinned; Black",
    "name": "Edhem",
    "origin": "Arabic,Bosnian",
    "religion": "Islam",
    "soundUrl": "https://cdn2.momjunction.com/wp-content/uploads/baby-names/audio_files/Edhem-arabic.mp3"
  },
  {
    "gender": "Boy",
    "id": 922457,
    "meaning": "Evolved; Grown; Developed; Advanced",
    "name": "Edhit",
    "origin": "Indian",
    "religion": "",
    "soundUrl": "https://cdn2.momjunction.com/wp-content/uploads/baby-names/audio_files/Edhit-hindi.mp3"
  },
  {
    "gender": "Boy",
    "id": 945604,
    "meaning": "A healthy and wealthy guardian",
    "name": "edik",
    "origin": "Russian",
    "religion": "Christianity",
    "soundUrl": "https://cdn2.momjunction.com/wp-content/uploads/baby-names/audio_files/edik-english.mp3"
  },
  {
    "gender": "Boy",
    "id": 945607,
    "meaning": "A noble and prosperous ruler",
    "name": "edilfred",
    "origin": "English",
    "religion": "Christianity",
    "soundUrl": "https://cdn2.momjunction.com/wp-content/uploads/baby-names/audio_files/edilfred-english.mp3"
  },
  {
    "gender": "Boy",
    "id": 945608,
    "meaning": "The one who is kind and pleasant",
    "name": "ediline",
    "origin": "German",
    "religion": "Christianity",
    "soundUrl": "https://cdn2.momjunction.com/wp-content/uploads/baby-names/audio_files/ediline-german.mp3"
  },
  {
    "gender": "Boy",
    "id": 945609,
    "meaning": "A strong and gracious person who is majestic",
    "name": "ediltrudis",
    "origin": "German",
    "religion": "Christianity",
    "soundUrl": "https://cdn2.momjunction.com/wp-content/uploads/baby-names/audio_files/ediltrudis-german.mp3"
  },
  {
    "gender": "Boy",
    "id": 945610,
    "meaning": "Delight; Place of pleasure",
    "name": "edin",
    "origin": "Hebrew",
    "religion": "Christianity",
    "soundUrl": "https://cdn2.momjunction.com/wp-content/uploads/baby-names/audio_files/edin-english.mp3"
  },
  {
    "gender": "Boy",
    "id": 945611,
    "meaning": "A lovely and prosperous friend; they are good people",
    "name": "edina",
    "origin": "German",
    "religion": "Christianity",
    "soundUrl": "https://cdn2.momjunction.com/wp-content/uploads/baby-names/audio_files/edina-german.mp3"
  },
  {
    "gender": "Boy",
    "id": 945613,
    "meaning": "Famous ruler; one who is ardent and efficient",
    "name": "edingu",
    "origin": "German",
    "religion": "Christianity",
    "soundUrl": "https://cdn2.momjunction.com/wp-content/uploads/baby-names/audio_files/edingu-german.mp3"
  },
  {
    "gender": "Boy",
    "id": 945614,
    "meaning": "One who is a succesor of Edward",
    "name": "edison",
    "origin": "English",
    "religion": "Christianity",
    "soundUrl": "https://cdn2.momjunction.com/wp-content/uploads/baby-names/audio_files/edison-english.mp3"
  },
  {
    "gender": "Boy",
    "id": 945615,
    "meaning": "Joyous; Wealthy gift from a ruler",
    "name": "edit",
    "origin": "Anglo Saxon",
    "religion": "Christianity",
    "soundUrl": "https://cdn2.momjunction.com/wp-content/uploads/baby-names/audio_files/edit-english.mp3"
  },
  {
    "gender": "Boy",
    "id": 945623,
    "meaning": "Of high position; they have a lavish lifestyle",
    "name": "ediz",
    "origin": "Turkish",
    "religion": "Christianity",
    "soundUrl": "https://cdn2.momjunction.com/wp-content/uploads/baby-names/audio_files/ediz-english.mp3"
  },
  {
    "gender": "Boy",
    "id": 945626,
    "meaning": "A rich friend; popular and friendly",
    "name": "edlin",
    "origin": "Anglo Saxon",
    "religion": "Christianity",
    "soundUrl": "https://cdn2.momjunction.com/wp-content/uploads/baby-names/audio_files/edlin-english.mp3"
  },
  {
    "gender": "Boy",
    "id": 945627,
    "meaning": "One who is like a rich waterfall",
    "name": "edlyn",
    "origin": "German",
    "religion": "Christianity",
    "soundUrl": "https://cdn2.momjunction.com/wp-content/uploads/baby-names/audio_files/edlyn-german.mp3"
  },
  {
    "gender": "Boy",
    "id": 945628,
    "meaning": "A prosperous guardian; one who shows light and way",
    "name": "edma",
    "origin": "English",
    "religion": "Christianity",
    "soundUrl": "https://cdn2.momjunction.com/wp-content/uploads/baby-names/audio_files/edma-english.mp3"
  }
]