[
  {
    "gender": "Boy",
    "id": 958573,
    "meaning": "A man who is from the white fortress",
    "name": "hwitloc",
    "origin": "English",
    "religion": "Judaism",
    "soundUrl": "https://cdn2.momjunction.com/wp-content/uploads/baby-names/audio_files/hwitloc-english.mp3"
  },
  {
    "gender": "Boy",
    "id": 958574,
    "meaning": "One who is a white man",
    "name": "hwitmann",
    "origin": "English",
    "religion": "Christianity",
    "soundUrl": "https://cdn2.momjunction.com/wp-content/uploads/baby-names/audio_files/hwitmann-english.mp3"
  },
  {
    "gender": "Boy",
    "id": 958575,
    "meaning": "Life itself",
    "name": "hy",
    "origin": "Hebrew",
    "religion": "Christianity",
    "soundUrl": "https://cdn2.momjunction.com/wp-content/uploads/baby-names/audio_files/hy-english.mp3"
  },
  {
    "gender": "Boy",
    "id": 958576,
    "meaning": "Blue larkspur flower; Precious stone",
    "name": "hyacinth",
    "origin": "Greek",
    "religion": "Christianity,Greek",
    "soundUrl": "https://cdn2.momjunction.com/wp-content/uploads/baby-names/audio_files/hyacinth-english.mp3"
  },
  {
    "gender": "Boy",
    "id": 958578,
    "meaning": "A boy from the high gate",
    "name": "hyatt",
    "origin": "English",
    "religion": "Judaism",
    "soundUrl": "https://cdn2.momjunction.com/wp-content/uploads/baby-names/audio_files/hyatt-english.mp3"
  },
  {
    "gender": "Boy",
    "id": 958580,
    "meaning": "He is a God",
    "name": "hycga",
    "origin": "English",
    "religion": "Christianity",
    "soundUrl": "https://cdn2.momjunction.com/wp-content/uploads/baby-names/audio_files/hycga-english.mp3"
  },
  {
    "gender": "Boy",
    "id": 958581,
    "meaning": "A Boy who is like a lion",
    "name": "hydar",
    "origin": "Arabic",
    "religion": "Christianity",
    "soundUrl": "https://cdn2.momjunction.com/wp-content/uploads/baby-names/audio_files/hydar-arabic.mp3"
  },
  {
    "gender": "Boy",
    "id": 958582,
    "meaning": "One who hides",
    "name": "hyde",
    "origin": "English",
    "religion": "Christianity",
    "soundUrl": "https://cdn2.momjunction.com/wp-content/uploads/baby-names/audio_files/hyde-english.mp3"
  },
  {
    "gender": "Boy",
    "id": 958583,
    "meaning": "A British male name",
    "name": "hydica",
    "origin": "English",
    "religion": "Christianity",
    "soundUrl": "https://cdn2.momjunction.com/wp-content/uploads/baby-names/audio_files/hydica-english.mp3"
  },
  {
    "gender": "Boy",
    "id": 958584,
    "meaning": "A bright and intelligent man",
    "name": "hye",
    "origin": "Korean",
    "religion": "Christianity",
    "soundUrl": "https://cdn2.momjunction.com/wp-content/uploads/baby-names/audio_files/hye-english.mp3"
  },
  {
    "gender": "Boy",
    "id": 958586,
    "meaning": "One who plays spirit and mind games",
    "name": "hygelac",
    "origin": "English",
    "religion": "Christianity",
    "soundUrl": "https://cdn2.momjunction.com/wp-content/uploads/baby-names/audio_files/hygelac-english.mp3"
  },
  {
    "gender": "Boy",
    "id": 958589,
    "meaning": "One who protects the battle",
    "name": "hyldeiard",
    "origin": "German",
    "religion": "Christianity",
    "soundUrl": "https://cdn2.momjunction.com/wp-content/uploads/baby-names/audio_files/hyldeiard-german.mp3"
  },
  {
    "gender": "Boy",
    "id": 958590,
    "meaning": "A warrior or a hero from battle",
    "name": "hyldeihera",
    "origin": "Greek",
    "religion": "Christianity",
    "soundUrl": "https://cdn2.momjunction.com/wp-content/uploads/baby-names/audio_files/hyldeihera-english.mp3"
  },
  {
    "gender": "Boy",
    "id": 958592,
    "meaning": "To be a man; A male",
    "name": "hyman",
    "origin": "Hebrew",
    "religion": "Christianity",
    "soundUrl": "https://cdn2.momjunction.com/wp-content/uploads/baby-names/audio_files/hyman-english.mp3"
  },
  {
    "gender": "Boy",
    "id": 958593,
    "meaning": "God of marriage",
    "name": "hymen",
    "origin": "Greek",
    "religion": "Christianity",
    "soundUrl": "https://cdn2.momjunction.com/wp-content/uploads/baby-names/audio_files/hymen-english.mp3"
  },
  {
    "gender": "Boy",
    "id": 958594,
    "meaning": "The life; To exist",
    "name": "hymie",
    "origin": "Hebrew",
    "religion": "Judaism",
    "soundUrl": "https://cdn2.momjunction.com/wp-content/uploads/baby-names/audio_files/hymie-english.mp3"
  },
  {
    "gender": "Boy",
    "id": 958595,
    "meaning": "A sensitive, creative, and desirable being",
    "name": "Hynala",
    "origin": "Indian",
    "religion": "Christianity",
    "soundUrl": "https://cdn2.momjunction.com/wp-content/uploads/baby-names/audio_files/Hynala-hindi.mp3"
  },
  {
    "gender": "Boy",
    "id": 924343,
    "meaning": "Helpful soldier; A soldier who is very helpful; A derivative of Hyousuke",
    "name": "Hyousuke",
    "origin": "Japanese",
    "religion": "",
    "soundUrl": "https://cdn2.momjunction.com/wp-content/uploads/baby-names/audio_files/Hyousuke-english.mp3"
  },
  {
    "gender": "Boy",
    "id": 958598,
    "meaning": "A supreme being",
    "name": "hyperion",
    "origin": "Greek",
    "religion": "Christianity",
    "soundUrl": "https://cdn2.momjunction.com/wp-content/uploads/baby-names/audio_files/hyperion-english.mp3"
  },
  {
    "gender": "Boy",
    "id": 924344,
    "meaning": "Letting horses loose",
    "name": "Hypolite",
    "origin": "",
    "religion": "",
    "soundUrl": "https://cdn2.momjunction.com/wp-content/uploads/baby-names/audio_files/Hypolite-english.mp3"
  },
  {
    "gender": "Boy",
    "id": 924345,
    "meaning": "Sacred name; Holy name; Latin form of Jerome; One with a sacred name",
    "name": "Hyroniemus",
    "origin": "Greek",
    "religion": "",
    "soundUrl": "https://cdn2.momjunction.com/wp-content/uploads/baby-names/audio_files/Hyroniemus-english.mp3"
  },
  {
    "gender": "Boy",
    "id": 924346,
    "meaning": "My brother is exalted; A spelling variant of Hiram;  A variant of Achiram",
    "name": "Hyrum",
    "origin": "Hebrew",
    "religion": "",
    "soundUrl": "https://cdn2.momjunction.com/wp-content/uploads/baby-names/audio_files/Hyrum-english.mp3"
  },
  {
    "gender": "Boy",
    "id": 924347,
    "meaning": "Flourishing spring; A name after an English tea merchant",
    "name": "Hyson",
    "origin": "Chinese",
    "religion": "",
    "soundUrl": "https://cdn2.momjunction.com/wp-content/uploads/baby-names/audio_files/Hyson-english.mp3"
  },
  {
    "gender": "Boy",
    "id": 958601,
    "meaning": "An english male name",
    "name": "hytha",
    "origin": "English",
    "religion": "Christianity",
    "soundUrl": "https://cdn2.momjunction.com/wp-content/uploads/baby-names/audio_files/hytha-english.mp3"
  },
  {
    "gender": "Boy",
    "id": 958602,
    "meaning": "The clearing of a woodland by man",
    "name": "hyttin",
    "origin": "English",
    "religion": "Christianity",
    "soundUrl": "https://cdn2.momjunction.com/wp-content/uploads/baby-names/audio_files/hyttin-english.mp3"
  },
  {
    "gender": "Boy",
    "id": 989351,
    "meaning": "Radiant",
    "name": "Hyuk",
    "origin": "Korean",
    "religion": "Christianity",
    "soundUrl": "https://cdn2.momjunction.com/wp-content/uploads/baby-names/audio_files/Hyuk-english.mp3"
  },
  {
    "gender": "Boy",
    "id": 924349,
    "meaning": "Wise; Astute; Intelligent; Shrewd; Expert; Clever",
    "name": "Hyun Ki",
    "origin": "Korean",
    "religion": "",
    "soundUrl": "https://cdn2.momjunction.com/wp-content/uploads/baby-names/audio_files/Hyun%20Ki-english.mp3"
  },
  {
    "gender": "Boy",
    "id": 924350,
    "meaning": "Clever; Smart; Brilliant",
    "name": "Hyun Shik",
    "origin": "Korean",
    "religion": "",
    "soundUrl": "https://cdn2.momjunction.com/wp-content/uploads/baby-names/audio_files/Hyun%20Shik-english.mp3"
  },
  {
    "gender": "Boy",
    "id": 924351,
    "meaning": "Eminent; Conspicuous; A variant of the name Howell",
    "name": "Hywel",
    "origin": "Welsh",
    "religion": "",
    "soundUrl": "https://cdn2.momjunction.com/wp-content/uploads/baby-names/audio_files/Hywel-english.mp3"
  },
  {
    "gender": "Boy",
    "id": 1000209,
    "meaning": "Georgian form of Jacob; Supplanter",
    "name": "Iakob",
    "origin": "Georgian",
    "religion": "Christianity",
    "soundUrl": "https://cdn2.momjunction.com/wp-content/uploads/baby-names/audio_files/Iakob-english.mp3"
  },
  {
    "gender": "Boy",
    "id": 1000837,
    "meaning": "God is gracious",
    "name": "Ian",
    "origin": "Latin America",
    "religion": "Christianity",
    "soundUrl": "https://cdn2.momjunction.com/wp-content/uploads/baby-names/audio_files/Ian-english.mp3"
  },
  {
    "gender": "Boy",
    "id": 990068,
    "meaning": "Romanian form of John; Yahweh is gracious",
    "name": "Iancu",
    "origin": "Hebrew,Romanian",
    "religion": "Judaism",
    "soundUrl": "https://cdn2.momjunction.com/wp-content/uploads/baby-names/audio_files/Iancu-english.mp3"
  },
  {
    "gender": "Boy",
    "id": 989176,
    "meaning": "To descend; The descendant",
    "name": "Iarere",
    "origin": "Maori",
    "religion": "Christianity",
    "soundUrl": "https://cdn2.momjunction.com/wp-content/uploads/baby-names/audio_files/Iarere-english.mp3"
  },
  {
    "gender": "Boy",
    "id": 995861,
    "meaning": "Ash tree",
    "name": "Iassen",
    "origin": "Bulgarian",
    "religion": "Christianity",
    "soundUrl": "https://cdn2.momjunction.com/wp-content/uploads/baby-names/audio_files/Iassen-english.mp3"
  },
  {
    "gender": "Boy",
    "id": 995864,
    "meaning": "Sycamore",
    "name": "Iavor",
    "origin": "Bulgarian",
    "religion": "Christianity",
    "soundUrl": "https://cdn2.momjunction.com/wp-content/uploads/baby-names/audio_files/Iavor-english.mp3"
  },
  {
    "gender": "Boy",
    "id": 989754,
    "meaning": "Worshiper of Allah; Devoted servant of Allah",
    "name": "Ibad ur Rehman",
    "origin": "Afghan,Arabic",
    "religion": "Islam",
    "soundUrl": "https://cdn2.momjunction.com/wp-content/uploads/baby-names/audio_files/Ibad%20ur%20Rehman-english.mp3"
  },
  {
    "gender": "Boy",
    "id": 993628,
    "meaning": "Harmony",
    "name": "Iben",
    "origin": "Canadian,Igbo",
    "religion": "Christianity",
    "soundUrl": "https://cdn2.momjunction.com/wp-content/uploads/baby-names/audio_files/Iben-english.mp3"
  },
  {
    "gender": "Boy",
    "id": 988413,
    "meaning": "Father of many",
    "name": "Ibrahim",
    "origin": "Arabic,Cyprus",
    "religion": "Islam",
    "soundUrl": "https://cdn2.momjunction.com/wp-content/uploads/baby-names/audio_files/Ibrahim-arabic.mp3"
  },
  {
    "gender": "Boy",
    "id": 991172,
    "meaning": "A younger brother",
    "name": "Iccauhtli",
    "origin": "Nahuatl",
    "religion": "Christianity",
    "soundUrl": "https://cdn2.momjunction.com/wp-content/uploads/baby-names/audio_files/Iccauhtli-english.mp3"
  },
  {
    "gender": "Boy",
    "id": 1000794,
    "meaning": "Frozen water or liquid",
    "name": "Ice",
    "origin": "Thai",
    "religion": "",
    "soundUrl": "https://cdn2.momjunction.com/wp-content/uploads/baby-names/audio_files/Ice-english.mp3"
  },
  {
    "gender": "Boy",
    "id": 999772,
    "meaning": "Secret",
    "name": "Ichtacka",
    "origin": "Aztec",
    "religion": "",
    "soundUrl": "https://cdn2.momjunction.com/wp-content/uploads/baby-names/audio_files/Ichtacka-english.mp3"
  },
  {
    "gender": "Boy",
    "id": 989505,
    "meaning": "Bright and luminous",
    "name": "Idhant",
    "origin": "Malayalam,Sanskrit",
    "religion": "Hindu",
    "soundUrl": "https://cdn2.momjunction.com/wp-content/uploads/baby-names/audio_files/Idhant-english.mp3"
  },
  {
    "gender": "Boy",
    "id": 990708,
    "meaning": "The second child born after twins",
    "name": "Idogbe",
    "origin": "Nigerian,Yoruba",
    "religion": "",
    "soundUrl": "https://cdn2.momjunction.com/wp-content/uploads/baby-names/audio_files/Idogbe-english.mp3"
  },
  {
    "gender": "Boy",
    "id": 997408,
    "meaning": "To comprehend; To understand",
    "name": "Idrak",
    "origin": "Arabic,Malay",
    "religion": "Islam",
    "soundUrl": "https://cdn2.momjunction.com/wp-content/uploads/baby-names/audio_files/Idrak-arabic.mp3"
  },
  {
    "gender": "Boy",
    "id": 988776,
    "meaning": "Variant of Idris; One who instructs or teaches",
    "name": "Idrees",
    "origin": "Arabic,Lebanese",
    "religion": "Islam",
    "soundUrl": "https://cdn2.momjunction.com/wp-content/uploads/baby-names/audio_files/Idrees-arabic.mp3"
  },
  {
    "gender": "Boy",
    "id": 989177,
    "meaning": "The Lord judges",
    "name": "Iehohapata",
    "origin": "Maori",
    "religion": "Christianity",
    "soundUrl": "https://cdn2.momjunction.com/wp-content/uploads/baby-names/audio_files/Iehohapata-english.mp3"
  },
  {
    "gender": "Boy",
    "id": 989178,
    "meaning": "God is gracious and merciful",
    "name": "Ieni",
    "origin": "Maori",
    "religion": "Christianity",
    "soundUrl": "https://cdn2.momjunction.com/wp-content/uploads/baby-names/audio_files/Ieni-english.mp3"
  },
  {
    "gender": "Boy",
    "id": 997409,
    "meaning": "Name of a Muslim prophet",
    "name": "Iesa",
    "origin": "Arabic,Malay",
    "religion": "Islam",
    "soundUrl": "https://cdn2.momjunction.com/wp-content/uploads/baby-names/audio_files/Iesa-arabic.mp3"
  },
  {
    "gender": "Boy",
    "id": 989179,
    "meaning": "Chaste or unmarried",
    "name": "Ietepere",
    "origin": "Maori",
    "religion": "Christianity",
    "soundUrl": "https://cdn2.momjunction.com/wp-content/uploads/baby-names/audio_files/Ietepere-english.mp3"
  },
  {
    "gender": "Boy",
    "id": 989180,
    "meaning": "Pre-eminence",
    "name": "Ietoro",
    "origin": "Maori",
    "religion": "Christianity",
    "soundUrl": "https://cdn2.momjunction.com/wp-content/uploads/baby-names/audio_files/Ietoro-english.mp3"
  },
  {
    "gender": "Boy",
    "id": 987627,
    "meaning": "Love; Someone who is born with an innate desire to love and be loved",
    "name": "Ife",
    "origin": "African,Jamaican",
    "religion": "Christianity",
    "soundUrl": "https://cdn2.momjunction.com/wp-content/uploads/baby-names/audio_files/Ife-english.mp3"
  },
  {
    "gender": "Boy",
    "id": 996768,
    "meaning": "God is most powerful; No one is greater than god.",
    "name": "Ifeanyichukwu",
    "origin": "Igbo,Nigerian",
    "religion": "Christianity",
    "soundUrl": "https://cdn2.momjunction.com/wp-content/uploads/baby-names/audio_files/Ifeanyichukwu-english.mp3"
  },
  {
    "gender": "Boy",
    "id": 990713,
    "meaning": "The light of God",
    "name": "Ifechi",
    "origin": "Igbo,Nigerian",
    "religion": "Christianity",
    "soundUrl": "https://cdn2.momjunction.com/wp-content/uploads/baby-names/audio_files/Ifechi-english.mp3"
  },
  {
    "gender": "Boy",
    "id": 996771,
    "meaning": "What God has written",
    "name": "Ifechukwude",
    "origin": "Igbo,Nigerian",
    "religion": "Christianity",
    "soundUrl": "https://cdn2.momjunction.com/wp-content/uploads/baby-names/audio_files/Ifechukwude-english.mp3"
  },
  {
    "gender": "Boy",
    "id": 996228,
    "meaning": "A beautiful love",
    "name": "Ifelewa",
    "origin": "Yoruba",
    "religion": "Christianity",
    "soundUrl": "https://cdn2.momjunction.com/wp-content/uploads/baby-names/audio_files/Ifelewa-english.mp3"
  },
  {
    "gender": "Boy",
    "id": 996773,
    "meaning": "What I asked of the Lord",
    "name": "Ifemyolunna",
    "origin": "Igbo,Nigerian",
    "religion": "Christianity",
    "soundUrl": "https://cdn2.momjunction.com/wp-content/uploads/baby-names/audio_files/Ifemyolunna-english.mp3"
  },
  {
    "gender": "Boy",
    "id": 997410,
    "meaning": "Time; Season; Weather",
    "name": "Iffaan",
    "origin": "Arabic,Malay",
    "religion": "Islam",
    "soundUrl": "https://cdn2.momjunction.com/wp-content/uploads/baby-names/audio_files/Iffaan-arabic.mp3"
  },
  {
    "gender": "Boy",
    "id": 999340,
    "meaning": "Abandoned hearth; Fireplace",
    "name": "Igaliko",
    "origin": "Greenlandic",
    "religion": "Christianity",
    "soundUrl": "https://cdn2.momjunction.com/wp-content/uploads/baby-names/audio_files/Igaliko-english.mp3"
  },
  {
    "gender": "Boy",
    "id": 1000572,
    "meaning": "The poor takes the blame",
    "name": "Igberaharha",
    "origin": "Nigerian,Urhobo",
    "religion": "Christianity",
    "soundUrl": "https://cdn2.momjunction.com/wp-content/uploads/baby-names/audio_files/Igberaharha-english.mp3"
  },
  {
    "gender": "Boy",
    "id": 999341,
    "meaning": "Throat",
    "name": "Iggiaq",
    "origin": "Greenlandic",
    "religion": "Christianity",
    "soundUrl": "https://cdn2.momjunction.com/wp-content/uploads/baby-names/audio_files/Iggiaq-english.mp3"
  },
  {
    "gender": "Boy",
    "id": 1000573,
    "meaning": "Money intoxicates the wealthy",
    "name": "Ighomuedafe",
    "origin": "Nigerian,Urhobo",
    "religion": "Christianity",
    "soundUrl": "https://cdn2.momjunction.com/wp-content/uploads/baby-names/audio_files/Ighomuedafe-english.mp3"
  },
  {
    "gender": "Boy",
    "id": 1000574,
    "meaning": "There is joy in riches",
    "name": "Ighovavwerhe",
    "origin": "Nigerian,Urhobo",
    "religion": "Christianity",
    "soundUrl": "https://cdn2.momjunction.com/wp-content/uploads/baby-names/audio_files/Ighovavwerhe-english.mp3"
  },
  {
    "gender": "Boy",
    "id": 999557,
    "meaning": "Slovene form of Ignatius; Fire",
    "name": "Ignacij",
    "origin": "Slovene",
    "religion": "Christianity",
    "soundUrl": "https://cdn2.momjunction.com/wp-content/uploads/baby-names/audio_files/Ignacij-english.mp3"
  },
  {
    "gender": "Boy",
    "id": 1001043,
    "meaning": "Variation of Ignacio which means fiery",
    "name": "Ignasio",
    "origin": "Spanish",
    "religion": "Christianity",
    "soundUrl": "https://cdn2.momjunction.com/wp-content/uploads/baby-names/audio_files/Ignasio-english.mp3"
  },
  {
    "gender": "Boy",
    "id": 988455,
    "meaning": "Warrior; Army",
    "name": "Igor",
    "origin": "Old Norse,Russian,Ukrainian",
    "religion": "Christianity",
    "soundUrl": "https://cdn2.momjunction.com/wp-content/uploads/baby-names/audio_files/Igor-english.mp3"
  },
  {
    "gender": "Boy",
    "id": 996777,
    "meaning": "Strength in numbers",
    "name": "Igwebuike",
    "origin": "Igbo,Nigerian",
    "religion": "",
    "soundUrl": "https://cdn2.momjunction.com/wp-content/uploads/baby-names/audio_files/Igwebuike-english.mp3"
  },
  {
    "gender": "Boy",
    "id": 989181,
    "meaning": "God is salvation",
    "name": "Ihaia",
    "origin": "Maori",
    "religion": "Christianity",
    "soundUrl": "https://cdn2.momjunction.com/wp-content/uploads/baby-names/audio_files/Ihaia-english.mp3"
  },
  {
    "gender": "Boy",
    "id": 989182,
    "meaning": "He will laugh",
    "name": "Ihaka",
    "origin": "Maori",
    "religion": "Christianity",
    "soundUrl": "https://cdn2.momjunction.com/wp-content/uploads/baby-names/audio_files/Ihaka-english.mp3"
  },
  {
    "gender": "Boy",
    "id": 988148,
    "meaning": "God’s grace",
    "name": "Ihan",
    "origin": "Argentina",
    "religion": "Christianity",
    "soundUrl": "https://cdn2.momjunction.com/wp-content/uploads/baby-names/audio_files/Ihan-english.mp3"
  },
  {
    "gender": "Boy",
    "id": 996778,
    "meaning": "Precious; What everyone seeks",
    "name": "Iheanacho",
    "origin": "Igbo,Nigerian",
    "religion": "",
    "soundUrl": "https://cdn2.momjunction.com/wp-content/uploads/baby-names/audio_files/Iheanacho-english.mp3"
  },
  {
    "gender": "Boy",
    "id": 988779,
    "meaning": "One who has a splendid or magnificent personality",
    "name": "Ihtishaam",
    "origin": "Arabic,Lebanese",
    "religion": "Islam",
    "soundUrl": "https://cdn2.momjunction.com/wp-content/uploads/baby-names/audio_files/Ihtishaam-arabic.mp3"
  },
  {
    "gender": "Boy",
    "id": 989184,
    "meaning": "God rescues",
    "name": "Ihu",
    "origin": "Maori",
    "religion": "Christianity",
    "soundUrl": "https://cdn2.momjunction.com/wp-content/uploads/baby-names/audio_files/Ihu-english.mp3"
  },
  {
    "gender": "Boy",
    "id": 999342,
    "meaning": "Greenlandic variant of Îsaia; God is salvation",
    "name": "Iisaja",
    "origin": "Greenlandic",
    "religion": "Christianity",
    "soundUrl": "https://cdn2.momjunction.com/wp-content/uploads/baby-names/audio_files/Iisaja-english.mp3"
  },
  {
    "gender": "Boy",
    "id": 999343,
    "meaning": "Moon",
    "name": "Ijaakaaq",
    "origin": "Greenlandic",
    "religion": "Christianity",
    "soundUrl": "https://cdn2.momjunction.com/wp-content/uploads/baby-names/audio_files/Ijaakaaq-english.mp3"
  },
  {
    "gender": "Boy",
    "id": 988780,
    "meaning": "Miracle; Astonishment; Magnanimity",
    "name": "Ijaaz",
    "origin": "Arabic,Lebanese",
    "religion": "Islam",
    "soundUrl": "https://cdn2.momjunction.com/wp-content/uploads/baby-names/audio_files/Ijaaz-arabic.mp3"
  },
  {
    "gender": "Boy",
    "id": 989506,
    "meaning": "A name of Lord Vishnu",
    "name": "Ijay",
    "origin": "Malayalam,Sanskrit",
    "religion": "Hindu",
    "soundUrl": "https://cdn2.momjunction.com/wp-content/uploads/baby-names/audio_files/Ijay-english.mp3"
  },
  {
    "gender": "Boy",
    "id": 988781,
    "meaning": "One who is chosen; Elected or approved",
    "name": "Ijtiba",
    "origin": "Arabic,Lebanese",
    "religion": "Islam",
    "soundUrl": "https://cdn2.momjunction.com/wp-content/uploads/baby-names/audio_files/Ijtiba-arabic.mp3"
  },
  {
    "gender": "Boy",
    "id": 990737,
    "meaning": "The power of God",
    "name": "Ikechukwu",
    "origin": "Igbo,Nigerian",
    "religion": "Christianity",
    "soundUrl": "https://cdn2.momjunction.com/wp-content/uploads/baby-names/audio_files/Ikechukwu-english.mp3"
  },
  {
    "gender": "Boy",
    "id": 996783,
    "meaning": "Strength of the nation",
    "name": "Ikemba",
    "origin": "Igbo,Nigerian",
    "religion": "",
    "soundUrl": "https://cdn2.momjunction.com/wp-content/uploads/baby-names/audio_files/Ikemba-english.mp3"
  },
  {
    "gender": "Boy",
    "id": 999017,
    "meaning": "A form of Ignatius; Fiery one",
    "name": "Ikenasio",
    "origin": "Polynesian,Tongan",
    "religion": "Christianity",
    "soundUrl": "https://cdn2.momjunction.com/wp-content/uploads/baby-names/audio_files/Ikenasio-english.mp3"
  },
  {
    "gender": "Boy",
    "id": 1001044,
    "meaning": "Visitation; Visitor",
    "name": "Iker",
    "origin": "Basque",
    "religion": "Christianity",
    "soundUrl": "https://cdn2.momjunction.com/wp-content/uploads/baby-names/audio_files/Iker-english.mp3"
  },
  {
    "gender": "Boy",
    "id": 988782,
    "meaning": "A man with good demeanor and moral virtues",
    "name": "Ikhlaaq",
    "origin": "Arabic,Lebanese",
    "religion": "Islam",
    "soundUrl": "https://cdn2.momjunction.com/wp-content/uploads/baby-names/audio_files/Ikhlaaq-arabic.mp3"
  },
  {
    "gender": "Boy",
    "id": 999344,
    "meaning": "How sweet you are",
    "name": "Ikila",
    "origin": "Greenlandic",
    "religion": "Christianity",
    "soundUrl": "https://cdn2.momjunction.com/wp-content/uploads/baby-names/audio_files/Ikila-english.mp3"
  },
  {
    "gender": "Boy",
    "id": 998331,
    "meaning": "Pigeon",
    "name": "Ikrimah",
    "origin": "Arabic,Middle East",
    "religion": "Islam",
    "soundUrl": "https://cdn2.momjunction.com/wp-content/uploads/baby-names/audio_files/Ikrimah-arabic.mp3"
  },
  {
    "gender": "Boy",
    "id": 989507,
    "meaning": "Sight",
    "name": "Ikshan",
    "origin": "Malayalam,Sanskrit",
    "religion": "Hindu",
    "soundUrl": "https://cdn2.momjunction.com/wp-content/uploads/baby-names/audio_files/Ikshan-english.mp3"
  },
  {
    "gender": "Boy",
    "id": 989508,
    "meaning": "Sugarcane",
    "name": "Ikshu",
    "origin": "Malayalam,Sanskrit",
    "religion": "Hindu",
    "soundUrl": "https://cdn2.momjunction.com/wp-content/uploads/baby-names/audio_files/Ikshu-english.mp3"
  },
  {
    "gender": "Boy",
    "id": 989357,
    "meaning": "Superiority",
    "name": "Il",
    "origin": "Korean",
    "religion": "Christianity",
    "soundUrl": "https://cdn2.momjunction.com/wp-content/uploads/baby-names/audio_files/Il-english.mp3"
  },
  {
    "gender": "Boy",
    "id": 995873,
    "meaning": "Bulgarian form of Hilarion; Happy",
    "name": "Ilarion",
    "origin": "Bulgarian,Latin",
    "religion": "Christianity",
    "soundUrl": "https://cdn2.momjunction.com/wp-content/uploads/baby-names/audio_files/Ilarion-english.mp3"
  },
  {
    "gender": "Boy",
    "id": 988149,
    "meaning": "One who is battle ready",
    "name": "Ildefonso",
    "origin": "Argentina",
    "religion": "",
    "soundUrl": "https://cdn2.momjunction.com/wp-content/uploads/baby-names/audio_files/Ildefonso-english.mp3"
  },
  {
    "gender": "Boy",
    "id": 990071,
    "meaning": "My God is Yahweh",
    "name": "Ilei",
    "origin": "Hebrew,Romanian",
    "religion": "Judaism",
    "soundUrl": "https://cdn2.momjunction.com/wp-content/uploads/baby-names/audio_files/Ilei-english.mp3"
  },
  {
    "gender": "Boy",
    "id": 996234,
    "meaning": "Messenger of God",
    "name": "Iles",
    "origin": "Yoruba",
    "religion": "Christianity",
    "soundUrl": "https://cdn2.momjunction.com/wp-content/uploads/baby-names/audio_files/Iles-english.mp3"
  },
  {
    "gender": "Boy",
    "id": 987945,
    "meaning": "Lord of the earth",
    "name": "Ilesh",
    "origin": "Hindi,Marathi,Oriya",
    "religion": "Jainism",
    "soundUrl": "https://cdn2.momjunction.com/wp-content/uploads/baby-names/audio_files/Ilesh-hindi.mp3"
  },
  {
    "gender": "Boy",
    "id": 999774,
    "meaning": "He who shoots arrows at the sky",
    "name": "Ilhicamina",
    "origin": "Aztec",
    "religion": "Christianity",
    "soundUrl": "https://cdn2.momjunction.com/wp-content/uploads/baby-names/audio_files/Ilhicamina-english.mp3"
  },
  {
    "gender": "Boy",
    "id": 991188,
    "meaning": "He who shoots arrows at the sky; The name of a great Mexican king",
    "name": "Ilhikamina",
    "origin": "Nahuatl",
    "religion": "Christianity",
    "soundUrl": "https://cdn2.momjunction.com/wp-content/uploads/baby-names/audio_files/Ilhikamina-english.mp3"
  },
  {
    "gender": "Boy",
    "id": 1000210,
    "meaning": "My God is Yahweh",
    "name": "Ilia",
    "origin": "Georgian",
    "religion": "Christianity",
    "soundUrl": "https://cdn2.momjunction.com/wp-content/uploads/baby-names/audio_files/Ilia-english.mp3"
  },
  {
    "gender": "Boy",
    "id": 989612,
    "meaning": "Croatian form of Elijah; My God is Yahweh",
    "name": "Ilija",
    "origin": "Croatian,Hebrew",
    "religion": "Christianity",
    "soundUrl": "https://cdn2.momjunction.com/wp-content/uploads/baby-names/audio_files/Ilija-english.mp3"
  },
  {
    "gender": "Boy",
    "id": 997141,
    "meaning": "Aslak’s son",
    "name": "Illugi",
    "origin": "Norse,Norwegian",
    "religion": "Christianity",
    "soundUrl": "https://cdn2.momjunction.com/wp-content/uploads/baby-names/audio_files/Illugi-english.mp3"
  },
  {
    "gender": "Boy",
    "id": 988456,
    "meaning": "He is my god",
    "name": "Illya",
    "origin": "Hebrew,Ukrainian",
    "religion": "Judaism",
    "soundUrl": "https://cdn2.momjunction.com/wp-content/uploads/baby-names/audio_files/Illya-english.mp3"
  },
  {
    "gender": "Boy",
    "id": 1000858,
    "meaning": "Knowledge",
    "name": "Ilm",
    "origin": "Quranic",
    "religion": "Islam",
    "soundUrl": "https://cdn2.momjunction.com/wp-content/uploads/baby-names/audio_files/Ilm-english.mp3"
  },
  {
    "gender": "Boy",
    "id": 1000784,
    "meaning": "From Ilmarinen; The eternal hammerer; A god in Finnish mythology",
    "name": "Ilmari",
    "origin": "Finnish",
    "religion": "Christianity",
    "soundUrl": "https://cdn2.momjunction.com/wp-content/uploads/baby-names/audio_files/Ilmari-english.mp3"
  }
]