[
  {
    "gender": "Girl",
    "id": 974953,
    "meaning": "One who admirable and compassionate",
    "name": "panu",
    "origin": "Indian",
    "religion": "Judaism",
    "soundUrl": "https://cdn2.momjunction.com/wp-content/uploads/baby-names/audio_files/panu-hindi.mp3"
  },
  {
    "gender": "Girl",
    "id": 974955,
    "meaning": "One who is crowned in victory",
    "name": "panya",
    "origin": "African,Latin,Russian",
    "religion": "Judaism",
    "soundUrl": "https://cdn2.momjunction.com/wp-content/uploads/baby-names/audio_files/panya-english.mp3"
  },
  {
    "gender": "Girl",
    "id": 974957,
    "meaning": "The older twin",
    "name": "panyin",
    "origin": "African",
    "religion": "Judaism",
    "soundUrl": "https://cdn2.momjunction.com/wp-content/uploads/baby-names/audio_files/panyin-english.mp3"
  },
  {
    "gender": "Girl",
    "id": 927286,
    "meaning": "Small; Humble",
    "name": "Paola",
    "origin": "Italian,Latin,Spanish",
    "religion": "",
    "soundUrl": "https://cdn2.momjunction.com/wp-content/uploads/baby-names/audio_files/Paola-english.mp3"
  },
  {
    "gender": "Girl",
    "id": 974958,
    "meaning": "A small and passionate individual",
    "name": "paolina",
    "origin": "Italian,Portuguese",
    "religion": "Judaism",
    "soundUrl": "https://cdn2.momjunction.com/wp-content/uploads/baby-names/audio_files/paolina-english.mp3"
  },
  {
    "gender": "Girl",
    "id": 998992,
    "meaning": "She who is mischievously smart",
    "name": "Papahi",
    "origin": "Polynesian,Tongan",
    "religion": "Christianity",
    "soundUrl": "https://cdn2.momjunction.com/wp-content/uploads/baby-names/audio_files/Papahi-english.mp3"
  },
  {
    "gender": "Girl",
    "id": 991292,
    "meaning": "Nahuatl word for flag",
    "name": "Papan",
    "origin": "Nahuatl",
    "religion": "Christianity",
    "soundUrl": "https://cdn2.momjunction.com/wp-content/uploads/baby-names/audio_files/Papan-english.mp3"
  },
  {
    "gender": "Girl",
    "id": 974963,
    "meaning": "A wonderful butterfly; thrifty individual",
    "name": "papillon",
    "origin": "English",
    "religion": "Judaism",
    "soundUrl": "https://cdn2.momjunction.com/wp-content/uploads/baby-names/audio_files/papillon-english.mp3"
  },
  {
    "gender": "Girl",
    "id": 974964,
    "meaning": "Ivy; a passionate individual",
    "name": "papina",
    "origin": "Native American",
    "religion": "Judaism",
    "soundUrl": "https://cdn2.momjunction.com/wp-content/uploads/baby-names/audio_files/papina-english.mp3"
  },
  {
    "gender": "Girl",
    "id": 974965,
    "meaning": "A sweet singing bird; rare",
    "name": "papiya",
    "origin": "Indian",
    "religion": "Judaism",
    "soundUrl": "https://cdn2.momjunction.com/wp-content/uploads/baby-names/audio_files/papiya-hindi.mp3"
  },
  {
    "gender": "Girl",
    "id": 974969,
    "meaning": "A spice called pepper",
    "name": "paprika",
    "origin": "Greek",
    "religion": "Judaism",
    "soundUrl": "https://cdn2.momjunction.com/wp-content/uploads/baby-names/audio_files/paprika-english.mp3"
  },
  {
    "gender": "Girl",
    "id": 974970,
    "meaning": "An independent and free person",
    "name": "paquita",
    "origin": "Spanish",
    "religion": "Judaism",
    "soundUrl": "https://cdn2.momjunction.com/wp-content/uploads/baby-names/audio_files/paquita-english.mp3"
  },
  {
    "gender": "Girl",
    "id": 927290,
    "meaning": "Heavenly",
    "name": "Paradis",
    "origin": "English",
    "religion": "",
    "soundUrl": "https://cdn2.momjunction.com/wp-content/uploads/baby-names/audio_files/Paradis-english.mp3"
  },
  {
    "gender": "Girl",
    "id": 974979,
    "meaning": "Sweet and rhyming; A raagini",
    "name": "parajika",
    "origin": "Indian",
    "religion": "Judaism",
    "soundUrl": "https://cdn2.momjunction.com/wp-content/uploads/baby-names/audio_files/parajika-hindi.mp3"
  },
  {
    "gender": "Girl",
    "id": 927292,
    "meaning": "An ornamental plant",
    "name": "Paralee",
    "origin": "English",
    "religion": "",
    "soundUrl": "https://cdn2.momjunction.com/wp-content/uploads/baby-names/audio_files/Paralee-english.mp3"
  },
  {
    "gender": "Girl",
    "id": 927293,
    "meaning": "The best; Ultimate; Most Superior",
    "name": "Parama",
    "origin": "Indian",
    "religion": "Hindu",
    "soundUrl": "https://cdn2.momjunction.com/wp-content/uploads/baby-names/audio_files/Parama-hindi.mp3"
  },
  {
    "gender": "Girl",
    "id": 974999,
    "meaning": "One who is the supreme God; Durga",
    "name": "parameshwa",
    "origin": "Indian",
    "religion": "Judaism",
    "soundUrl": "https://cdn2.momjunction.com/wp-content/uploads/baby-names/audio_files/parameshwa-hindi.mp3"
  },
  {
    "gender": "Girl",
    "id": 927308,
    "meaning": "One of the many names of Goddess Durga",
    "name": "Parameshwari",
    "origin": "Indian",
    "religion": "Hindu",
    "soundUrl": "https://cdn2.momjunction.com/wp-content/uploads/baby-names/audio_files/Parameshwari-hindi.mp3"
  },
  {
    "gender": "Girl",
    "id": 975002,
    "meaning": "A name given to Goddess Durga",
    "name": "parameswari",
    "origin": "Indian",
    "religion": "Judaism",
    "soundUrl": "https://cdn2.momjunction.com/wp-content/uploads/baby-names/audio_files/parameswari-hindi.mp3"
  },
  {
    "gender": "Girl",
    "id": 927310,
    "meaning": "The highest song of bliss; Most divine song; Spiritually superior song",
    "name": "Paramgeet",
    "origin": "Indian",
    "religion": "Hindu",
    "soundUrl": "https://cdn2.momjunction.com/wp-content/uploads/baby-names/audio_files/Paramgeet-hindi.mp3"
  },
  {
    "gender": "Girl",
    "id": 927315,
    "meaning": "Friend of Others; Best Friend; Best Well Wisher",
    "name": "Paramita",
    "origin": "Indian",
    "religion": "Hindu",
    "soundUrl": "https://cdn2.momjunction.com/wp-content/uploads/baby-names/audio_files/Paramita-hindi.mp3"
  },
  {
    "gender": "Girl",
    "id": 927321,
    "meaning": "One uniting with the highest; One who is connected with the most ultimate and superior most Lord",
    "name": "Paramjog",
    "origin": "Indian",
    "religion": "Hindu",
    "soundUrl": "https://cdn2.momjunction.com/wp-content/uploads/baby-names/audio_files/Paramjog-hindi.mp3"
  },
  {
    "gender": "Girl",
    "id": 927322,
    "meaning": "The highest light; God\u0027s light; Ultimate divine brightness",
    "name": "Paramjot",
    "origin": "Indian",
    "religion": "Hindu",
    "soundUrl": "https://cdn2.momjunction.com/wp-content/uploads/baby-names/audio_files/Paramjot-hindi.mp3"
  },
  {
    "gender": "Girl",
    "id": 927326,
    "meaning": "Absorbed in the highest; God; One who is engrossed in the ultimate God",
    "name": "Paramleen",
    "origin": "Indian",
    "religion": "Hindu",
    "soundUrl": "https://cdn2.momjunction.com/wp-content/uploads/baby-names/audio_files/Paramleen-hindi.mp3"
  },
  {
    "gender": "Girl",
    "id": 975009,
    "meaning": "The succession of teachers to students",
    "name": "parampara",
    "origin": "Indian",
    "religion": "Judaism",
    "soundUrl": "https://cdn2.momjunction.com/wp-content/uploads/baby-names/audio_files/parampara-hindi.mp3"
  },
  {
    "gender": "Girl",
    "id": 975012,
    "meaning": "One who is at the highest worship point",
    "name": "paramsimran",
    "origin": "Indian",
    "religion": "Judaism",
    "soundUrl": "https://cdn2.momjunction.com/wp-content/uploads/baby-names/audio_files/paramsimran-hindi.mp3"
  },
  {
    "gender": "Girl",
    "id": 975014,
    "meaning": "One who is the most beautiful person",
    "name": "paramsundari",
    "origin": "Indian",
    "religion": "Judaism",
    "soundUrl": "https://cdn2.momjunction.com/wp-content/uploads/baby-names/audio_files/paramsundari-hindi.mp3"
  },
  {
    "gender": "Girl",
    "id": 927349,
    "meaning": "The Greatest Warrior; Ultimate Defender; Superior Fighter and Protector",
    "name": "Paramvir",
    "origin": "Indian",
    "religion": "Hindu",
    "soundUrl": "https://cdn2.momjunction.com/wp-content/uploads/baby-names/audio_files/Paramvir-hindi.mp3"
  },
  {
    "gender": "Girl",
    "id": 975019,
    "meaning": "One who is as soft as silk",
    "name": "parand",
    "origin": "Indian",
    "religion": "Judaism",
    "soundUrl": "https://cdn2.momjunction.com/wp-content/uploads/baby-names/audio_files/parand-hindi.mp3"
  },
  {
    "gender": "Girl",
    "id": 927359,
    "meaning": "Preparation; A variation of Paraskeve",
    "name": "Paraskevi",
    "origin": "Greek",
    "religion": "Greek",
    "soundUrl": "https://cdn2.momjunction.com/wp-content/uploads/baby-names/audio_files/Paraskevi-english.mp3"
  },
  {
    "gender": "Girl",
    "id": 927360,
    "meaning": "Touchstone",
    "name": "Parasmani",
    "origin": "Indian",
    "religion": "Hindu",
    "soundUrl": "https://cdn2.momjunction.com/wp-content/uploads/baby-names/audio_files/Parasmani-hindi.mp3"
  },
  {
    "gender": "Girl",
    "id": 975034,
    "meaning": "Swallow bird",
    "name": "parastoo",
    "origin": "Persian",
    "religion": "",
    "soundUrl": "https://cdn2.momjunction.com/wp-content/uploads/baby-names/audio_files/parastoo-english.mp3"
  },
  {
    "gender": "Girl",
    "id": 927361,
    "meaning": "Bird",
    "name": "Paravi",
    "origin": "Indian",
    "religion": "Hindu",
    "soundUrl": "https://cdn2.momjunction.com/wp-content/uploads/baby-names/audio_files/Paravi-hindi.mp3"
  },
  {
    "gender": "Girl",
    "id": 975041,
    "meaning": "Name of a Goddess who has greatest aura",
    "name": "parbani",
    "origin": "Indian",
    "religion": "Judaism",
    "soundUrl": "https://cdn2.momjunction.com/wp-content/uploads/baby-names/audio_files/parbani-hindi.mp3"
  },
  {
    "gender": "Girl",
    "id": 975042,
    "meaning": "One who is the daughter of the mountains",
    "name": "parbarti",
    "origin": "Indian",
    "religion": "Judaism",
    "soundUrl": "https://cdn2.momjunction.com/wp-content/uploads/baby-names/audio_files/parbarti-hindi.mp3"
  },
  {
    "gender": "Girl",
    "id": 927362,
    "meaning": "Capable; Skillful; Efficient; Intelligent and Brilliant",
    "name": "Parbeen",
    "origin": "Persian",
    "religion": "Zoroastrianism",
    "soundUrl": "https://cdn2.momjunction.com/wp-content/uploads/baby-names/audio_files/Parbeen-english.mp3"
  },
  {
    "gender": "Girl",
    "id": 975051,
    "meaning": "One who has the face of a fairy",
    "name": "pareechehr",
    "origin": "Arabic",
    "religion": "",
    "soundUrl": "https://cdn2.momjunction.com/wp-content/uploads/baby-names/audio_files/pareechehr-arabic.mp3"
  },
  {
    "gender": "Girl",
    "id": 975052,
    "meaning": "One with beautiful fairy-like face",
    "name": "pareerou",
    "origin": "Arabic",
    "religion": "Judaism",
    "soundUrl": "https://cdn2.momjunction.com/wp-content/uploads/baby-names/audio_files/pareerou-arabic.mp3"
  },
  {
    "gender": "Girl",
    "id": 975053,
    "meaning": "One who resembles a fairy",
    "name": "pareesa",
    "origin": "Arabic",
    "religion": "Judaism",
    "soundUrl": "https://cdn2.momjunction.com/wp-content/uploads/baby-names/audio_files/pareesa-arabic.mp3"
  },
  {
    "gender": "Girl",
    "id": 927986,
    "meaning": "Love; Affection; Compassion; The One Who Loves The Lord",
    "name": "pareet",
    "origin": "Indian",
    "religion": "Hindu",
    "soundUrl": "https://cdn2.momjunction.com/wp-content/uploads/baby-names/audio_files/pareet-hindi.mp3"
  },
  {
    "gender": "Girl",
    "id": 975054,
    "meaning": "A fairy-faced person",
    "name": "pareewash",
    "origin": "Arabic",
    "religion": "Judaism",
    "soundUrl": "https://cdn2.momjunction.com/wp-content/uploads/baby-names/audio_files/pareewash-arabic.mp3"
  },
  {
    "gender": "Girl",
    "id": 927371,
    "meaning": "Fairy; Angel; One who is filled with goodness and is like a life savior",
    "name": "Pari",
    "origin": "Indian",
    "religion": "Hindu",
    "soundUrl": "https://cdn2.momjunction.com/wp-content/uploads/baby-names/audio_files/Pari-hindi.mp3"
  },
  {
    "gender": "Girl",
    "id": 987885,
    "meaning": "A girl with a face as beautiful as a fairy",
    "name": "Parichehr",
    "origin": "Parsi",
    "religion": "Zoroastrianism",
    "soundUrl": "https://cdn2.momjunction.com/wp-content/uploads/baby-names/audio_files/Parichehr-english.mp3"
  },
  {
    "gender": "Girl",
    "id": 927374,
    "meaning": "Limit; Boundary; One who controls our life",
    "name": "Paridhi",
    "origin": "Indian",
    "religion": "Hindu",
    "soundUrl": "https://cdn2.momjunction.com/wp-content/uploads/baby-names/audio_files/Paridhi-hindi.mp3"
  },
  {
    "gender": "Girl",
    "id": 989874,
    "meaning": "Angel of flowers",
    "name": "Parigul",
    "origin": "Afghan,Arabic",
    "religion": "Islam",
    "soundUrl": "https://cdn2.momjunction.com/wp-content/uploads/baby-names/audio_files/Parigul-english.mp3"
  },
  {
    "gender": "Girl",
    "id": 975062,
    "meaning": "A beautiful fairy",
    "name": "parihan",
    "origin": "Arabic",
    "religion": "Judaism",
    "soundUrl": "https://cdn2.momjunction.com/wp-content/uploads/baby-names/audio_files/parihan-arabic.mp3"
  },
  {
    "gender": "Girl",
    "id": 975065,
    "meaning": "One with a fair soul",
    "name": "parijan",
    "origin": "Arabic",
    "religion": "Judaism",
    "soundUrl": "https://cdn2.momjunction.com/wp-content/uploads/baby-names/audio_files/parijan-arabic.mp3"
  },
  {
    "gender": "Girl",
    "id": 975069,
    "meaning": "One who is like the fairy queen",
    "name": "parikhan",
    "origin": "Indian",
    "religion": "Judaism",
    "soundUrl": "https://cdn2.momjunction.com/wp-content/uploads/baby-names/audio_files/parikhan-hindi.mp3"
  },
  {
    "gender": "Girl",
    "id": 975070,
    "meaning": "A fragrant and lovely human being",
    "name": "parimalan",
    "origin": "Indian",
    "religion": "Judaism",
    "soundUrl": "https://cdn2.momjunction.com/wp-content/uploads/baby-names/audio_files/parimalan-hindi.mp3"
  },
  {
    "gender": "Girl",
    "id": 927380,
    "meaning": "Fairy; Angel; One who is filled with goodness and is like a life saver",
    "name": "Parina",
    "origin": "Indian",
    "religion": "Hindu",
    "soundUrl": "https://cdn2.momjunction.com/wp-content/uploads/baby-names/audio_files/Parina-hindi.mp3"
  },
  {
    "gender": "Girl",
    "id": 975074,
    "meaning": "A charming and beautiful person",
    "name": "parinaz",
    "origin": "Arabic",
    "religion": "",
    "soundUrl": "https://cdn2.momjunction.com/wp-content/uploads/baby-names/audio_files/parinaz-arabic.mp3"
  },
  {
    "gender": "Girl",
    "id": 975077,
    "meaning": "A bird; one who is beautiful like a fairy",
    "name": "parineeti",
    "origin": "Indian",
    "religion": "Judaism",
    "soundUrl": "https://cdn2.momjunction.com/wp-content/uploads/baby-names/audio_files/parineeti-hindi.mp3"
  },
  {
    "gender": "Girl",
    "id": 927383,
    "meaning": "Complete; One who fulfills our life; One who brings completion and fulfillment in life",
    "name": "Parinita",
    "origin": "Indian",
    "religion": "Hindu",
    "soundUrl": "https://cdn2.momjunction.com/wp-content/uploads/baby-names/audio_files/Parinita-hindi.mp3"
  },
  {
    "gender": "Girl",
    "id": 1000247,
    "meaning": "Face like a fairy",
    "name": "Parirow",
    "origin": "Georgian",
    "religion": "Christianity",
    "soundUrl": "https://cdn2.momjunction.com/wp-content/uploads/baby-names/audio_files/Parirow-english.mp3"
  },
  {
    "gender": "Girl",
    "id": 927384,
    "meaning": "Angelic face; A derived name from Pari which means fairy",
    "name": "Parisa",
    "origin": "Indian",
    "religion": "Hindu",
    "soundUrl": "https://cdn2.momjunction.com/wp-content/uploads/baby-names/audio_files/Parisa-hindi.mp3"
  },
  {
    "gender": "Girl",
    "id": 927387,
    "meaning": "Extremely free; One who is independent and self-standing",
    "name": "Parivita",
    "origin": "Indian",
    "religion": "Hindu",
    "soundUrl": "https://cdn2.momjunction.com/wp-content/uploads/baby-names/audio_files/Parivita-hindi.mp3"
  },
  {
    "gender": "Girl",
    "id": 987747,
    "meaning": "A girl who is as beautiful as a fairy",
    "name": "Pariwarsh",
    "origin": "Pashto",
    "religion": "Islam",
    "soundUrl": "https://cdn2.momjunction.com/wp-content/uploads/baby-names/audio_files/Pariwarsh-english.mp3"
  },
  {
    "gender": "Girl",
    "id": 989875,
    "meaning": "Fairy-faced or angelic beauty",
    "name": "Pariwish",
    "origin": "Afghan,Arabic",
    "religion": "Islam",
    "soundUrl": "https://cdn2.momjunction.com/wp-content/uploads/baby-names/audio_files/Pariwish-english.mp3"
  },
  {
    "gender": "Girl",
    "id": 927389,
    "meaning": "Flower; Beautiful; Soft and Tender like a flower",
    "name": "Pariyat",
    "origin": "Indian",
    "religion": "Hindu",
    "soundUrl": "https://cdn2.momjunction.com/wp-content/uploads/baby-names/audio_files/Pariyat-hindi.mp3"
  },
  {
    "gender": "Girl",
    "id": 975089,
    "meaning": "One who is born out of a fairy",
    "name": "parizad",
    "origin": "Arabic",
    "religion": "Islam",
    "soundUrl": "https://cdn2.momjunction.com/wp-content/uploads/baby-names/audio_files/parizad-arabic.mp3"
  },
  {
    "gender": "Girl",
    "id": 975099,
    "meaning": "One who is employed in the park",
    "name": "parkes",
    "origin": "Anglo Saxon",
    "religion": "Judaism",
    "soundUrl": "https://cdn2.momjunction.com/wp-content/uploads/baby-names/audio_files/parkes-english.mp3"
  },
  {
    "gender": "Girl",
    "id": 987748,
    "meaning": "Dew or tiny droplets of water falling at night",
    "name": "Parkha",
    "origin": "Pashto",
    "religion": "Islam",
    "soundUrl": "https://cdn2.momjunction.com/wp-content/uploads/baby-names/audio_files/Parkha-english.mp3"
  },
  {
    "gender": "Girl",
    "id": 975103,
    "meaning": "One who is determined and has the preserving nature",
    "name": "parkir",
    "origin": "English",
    "religion": "Judaism",
    "soundUrl": "https://cdn2.momjunction.com/wp-content/uploads/baby-names/audio_files/parkir-english.mp3"
  },
  {
    "gender": "Girl",
    "id": 927393,
    "meaning": "Ploughman; Farmer; Son of the plough",
    "name": "Parlan",
    "origin": "English,Scottish",
    "religion": "",
    "soundUrl": "https://cdn2.momjunction.com/wp-content/uploads/baby-names/audio_files/Parlan-english.mp3"
  },
  {
    "gender": "Girl",
    "id": 975107,
    "meaning": "One who speaks very good",
    "name": "parley",
    "origin": "English",
    "religion": "Judaism",
    "soundUrl": "https://cdn2.momjunction.com/wp-content/uploads/baby-names/audio_files/parley-english.mp3"
  },
  {
    "gender": "Girl",
    "id": 927397,
    "meaning": "Princess; Royal descendant",
    "name": "Parmida",
    "origin": "Indian",
    "religion": "Hindu",
    "soundUrl": "https://cdn2.momjunction.com/wp-content/uploads/baby-names/audio_files/Parmida-hindi.mp3"
  },
  {
    "gender": "Girl",
    "id": 975112,
    "meaning": "Name of Arjuna\u0027s wife",
    "name": "parmila",
    "origin": "Indian",
    "religion": "Judaism",
    "soundUrl": "https://cdn2.momjunction.com/wp-content/uploads/baby-names/audio_files/parmila-hindi.mp3"
  },
  {
    "gender": "Girl",
    "id": 927398,
    "meaning": "God Of Gods; Ultimate God",
    "name": "Parmindar",
    "origin": "Indian",
    "religion": "Hindu",
    "soundUrl": "https://cdn2.momjunction.com/wp-content/uploads/baby-names/audio_files/Parmindar-hindi.mp3"
  },
  {
    "gender": "Girl",
    "id": 927401,
    "meaning": "Wisdom; Knowledge; Learning; Brilliance; Intelligence",
    "name": "Parmita",
    "origin": "Indian",
    "religion": "Hindu",
    "soundUrl": "https://cdn2.momjunction.com/wp-content/uploads/baby-names/audio_files/Parmita-hindi.mp3"
  },
  {
    "gender": "Girl",
    "id": 927402,
    "meaning": "One who has won over the ultimate; A variant spelling of Parmjeet",
    "name": "Parmjit",
    "origin": "Indian",
    "religion": "Hindu",
    "soundUrl": "https://cdn2.momjunction.com/wp-content/uploads/baby-names/audio_files/Parmjit-hindi.mp3"
  },
  {
    "gender": "Girl",
    "id": 975121,
    "meaning": "Married; Eyes like a leaf",
    "name": "parnakshi",
    "origin": "Indian",
    "religion": "Judaism",
    "soundUrl": "https://cdn2.momjunction.com/wp-content/uploads/baby-names/audio_files/parnakshi-hindi.mp3"
  },
  {
    "gender": "Girl",
    "id": 927403,
    "meaning": "Leafy beauty; One of many names of Goddess Parvathi",
    "name": "Parnashri",
    "origin": "Indian",
    "religion": "Hindu",
    "soundUrl": "https://cdn2.momjunction.com/wp-content/uploads/baby-names/audio_files/Parnashri-hindi.mp3"
  },
  {
    "gender": "Girl",
    "id": 975125,
    "meaning": "A sweet song-singing bird",
    "name": "parnavi",
    "origin": "Indian",
    "religion": "Judaism",
    "soundUrl": "https://cdn2.momjunction.com/wp-content/uploads/baby-names/audio_files/parnavi-hindi.mp3"
  },
  {
    "gender": "Girl",
    "id": 975127,
    "meaning": "Married; one who is idealistic and sensitive",
    "name": "parneet",
    "origin": "Indian",
    "religion": "Judaism",
    "soundUrl": "https://cdn2.momjunction.com/wp-content/uploads/baby-names/audio_files/parneet-hindi.mp3"
  },
  {
    "gender": "Girl",
    "id": 975130,
    "meaning": "One who is leafy and delicate",
    "name": "parni",
    "origin": "Indian",
    "religion": "Judaism",
    "soundUrl": "https://cdn2.momjunction.com/wp-content/uploads/baby-names/audio_files/parni-hindi.mp3"
  },
  {
    "gender": "Girl",
    "id": 975131,
    "meaning": "A creeper or a small leaf",
    "name": "parnik",
    "origin": "Indian",
    "religion": "Judaism",
    "soundUrl": "https://cdn2.momjunction.com/wp-content/uploads/baby-names/audio_files/parnik-hindi.mp3"
  },
  {
    "gender": "Girl",
    "id": 927404,
    "meaning": "A small leaf; One of many names of Goddess Parvati",
    "name": "Parnika",
    "origin": "Indian",
    "religion": "Hindu",
    "soundUrl": "https://cdn2.momjunction.com/wp-content/uploads/baby-names/audio_files/Parnika-hindi.mp3"
  },
  {
    "gender": "Girl",
    "id": 975132,
    "meaning": "Name given to an auspicious and beautiful nymph",
    "name": "parnita",
    "origin": "Indian",
    "religion": "Judaism",
    "soundUrl": "https://cdn2.momjunction.com/wp-content/uploads/baby-names/audio_files/parnita-hindi.mp3"
  },
  {
    "gender": "Girl",
    "id": 988809,
    "meaning": "Soft silk; A dress made of soft silk",
    "name": "Parniyan",
    "origin": "Arabic,Lebanese",
    "religion": "Islam",
    "soundUrl": "https://cdn2.momjunction.com/wp-content/uploads/baby-names/audio_files/Parniyan-arabic.mp3"
  },
  {
    "gender": "Girl",
    "id": 975133,
    "meaning": "Leafy; a fortunate individual",
    "name": "parno",
    "origin": "Indian",
    "religion": "Judaism",
    "soundUrl": "https://cdn2.momjunction.com/wp-content/uploads/baby-names/audio_files/parno-hindi.mp3"
  },
  {
    "gender": "Girl",
    "id": 975134,
    "meaning": "Pretty and beautiful person",
    "name": "paromarshi",
    "origin": "Indian",
    "religion": "Judaism",
    "soundUrl": "https://cdn2.momjunction.com/wp-content/uploads/baby-names/audio_files/paromarshi-hindi.mp3"
  },
  {
    "gender": "Girl",
    "id": 975135,
    "meaning": "A generous and neutral individual",
    "name": "paronel",
    "origin": "English",
    "religion": "Judaism",
    "soundUrl": "https://cdn2.momjunction.com/wp-content/uploads/baby-names/audio_files/paronel-english.mp3"
  },
  {
    "gender": "Girl",
    "id": 975136,
    "meaning": "Name of an Ayurvedic medicine",
    "name": "parpati",
    "origin": "Indian",
    "religion": "Judaism",
    "soundUrl": "https://cdn2.momjunction.com/wp-content/uploads/baby-names/audio_files/parpati-hindi.mp3"
  },
  {
    "gender": "Girl",
    "id": 975137,
    "meaning": "A clear sighted and clever individual",
    "name": "parris",
    "origin": "Anglo Saxon",
    "religion": "Judaism",
    "soundUrl": "https://cdn2.momjunction.com/wp-content/uploads/baby-names/audio_files/parris-english.mp3"
  },
  {
    "gender": "Girl",
    "id": 927406,
    "meaning": "Son of Harry",
    "name": "Parry",
    "origin": "Welsh",
    "religion": "",
    "soundUrl": "https://cdn2.momjunction.com/wp-content/uploads/baby-names/audio_files/Parry-english.mp3"
  },
  {
    "gender": "Girl",
    "id": 996660,
    "meaning": "Flake",
    "name": "Parsla",
    "origin": "Latvian",
    "religion": "Christianity",
    "soundUrl": "https://cdn2.momjunction.com/wp-content/uploads/baby-names/audio_files/Parsla-english.mp3"
  },
  {
    "gender": "Girl",
    "id": 975159,
    "meaning": "Name given to Goddess Sita",
    "name": "parthav",
    "origin": "Indian",
    "religion": "Judaism",
    "soundUrl": "https://cdn2.momjunction.com/wp-content/uploads/baby-names/audio_files/parthav-hindi.mp3"
  },
  {
    "gender": "Girl",
    "id": 927413,
    "meaning": "One of many names of Goddess Sita",
    "name": "Parthavi",
    "origin": "Indian",
    "religion": "Hindu",
    "soundUrl": "https://cdn2.momjunction.com/wp-content/uploads/baby-names/audio_files/Parthavi-hindi.mp3"
  },
  {
    "gender": "Girl",
    "id": 927414,
    "meaning": "Maiden; Virgin; A variant form of Parthenia",
    "name": "Parthena",
    "origin": "English,Greek",
    "religion": "Christianity,Greek",
    "soundUrl": "https://cdn2.momjunction.com/wp-content/uploads/baby-names/audio_files/Parthena-english.mp3"
  },
  {
    "gender": "Girl",
    "id": 975160,
    "meaning": "One who is a virgin and chaste",
    "name": "parthenia",
    "origin": "Greek",
    "religion": "Greek,Judaism",
    "soundUrl": "https://cdn2.momjunction.com/wp-content/uploads/baby-names/audio_files/parthenia-english.mp3"
  },
  {
    "gender": "Girl",
    "id": 927415,
    "meaning": "Maiden; Virgin; A variant form of Parthenia",
    "name": "Parthenope",
    "origin": "English,Greek",
    "religion": "Christianity,Greek",
    "soundUrl": "https://cdn2.momjunction.com/wp-content/uploads/baby-names/audio_files/Parthenope-english.mp3"
  },
  {
    "gender": "Girl",
    "id": 927416,
    "meaning": "One of many names of Goddess Sita",
    "name": "Parthivi",
    "origin": "Indian",
    "religion": "Hindu",
    "soundUrl": "https://cdn2.momjunction.com/wp-content/uploads/baby-names/audio_files/Parthivi-hindi.mp3"
  },
  {
    "gender": "Girl",
    "id": 975168,
    "meaning": "One who is a ray of light",
    "name": "parto",
    "origin": "Persian",
    "religion": "",
    "soundUrl": "https://cdn2.momjunction.com/wp-content/uploads/baby-names/audio_files/parto-english.mp3"
  },
  {
    "gender": "Girl",
    "id": 999501,
    "meaning": "Master; Furnished",
    "name": "Paru",
    "origin": "Gujarati,Sanskrit",
    "religion": "Hindu",
    "soundUrl": "https://cdn2.momjunction.com/wp-content/uploads/baby-names/audio_files/Paru-english.mp3"
  },
  {
    "gender": "Girl",
    "id": 1000124,
    "meaning": "She who is beautiful and intelligent",
    "name": "Parushi",
    "origin": "Sanskrit,South Indian",
    "religion": "Hindu",
    "soundUrl": "https://cdn2.momjunction.com/wp-content/uploads/baby-names/audio_files/Parushi-hindi.mp3"
  },
  {
    "gender": "Girl",
    "id": 975171,
    "meaning": "A strong and festive individual",
    "name": "parv",
    "origin": "Indian",
    "religion": "Judaism",
    "soundUrl": "https://cdn2.momjunction.com/wp-content/uploads/baby-names/audio_files/parv-hindi.mp3"
  },
  {
    "gender": "Girl",
    "id": 975172,
    "meaning": "A festive and strong individual",
    "name": "parva",
    "origin": "Indian",
    "religion": "Judaism",
    "soundUrl": "https://cdn2.momjunction.com/wp-content/uploads/baby-names/audio_files/parva-hindi.mp3"
  },
  {
    "gender": "Girl",
    "id": 975176,
    "meaning": "A butterfly; naughty and amazing",
    "name": "parvana",
    "origin": "Persian",
    "religion": "",
    "soundUrl": "https://cdn2.momjunction.com/wp-content/uploads/baby-names/audio_files/parvana-english.mp3"
  },
  {
    "gender": "Girl",
    "id": 975177,
    "meaning": "A rare and majestic butterfly",
    "name": "parvanah",
    "origin": "Persian",
    "religion": "Judaism",
    "soundUrl": "https://cdn2.momjunction.com/wp-content/uploads/baby-names/audio_files/parvanah-english.mp3"
  },
  {
    "gender": "Girl",
    "id": 927419,
    "meaning": "Like a Butterfly",
    "name": "Parvaneh",
    "origin": "Persian",
    "religion": "Zoroastrianism",
    "soundUrl": "https://cdn2.momjunction.com/wp-content/uploads/baby-names/audio_files/Parvaneh-english.mp3"
  }
]